Workbook
Name Slicer_Gender: #N/A
Name Slicer_Gender1: #N/A
Name Slicer_Months__Hiredate: #N/A

Sheet EMPLOYEE DASHBOARD
T2: EMPLOYEE DATA ANALYSIS
H27: Avg FAvg Female Salary $59,446 36% of workforceemale Salary $59,446 36% of workforce

Sheet STAFF
A1: Employee_ID | B1: First Name | C1: Last Name | D1: Gender | E1: State | F1: City | G1: Education Level | H1: Birthdate | I1: Hiredate | J1: Termdate | K1: Department | L1: Job Title | M1: Salary | N1: Atrrition status | O1: Performance Rating
A2: 00-10001272 | B2: Samuel | C2: Burgess | D2: Female | E2: West Virginia | F2: Huntington | G2: Bachelor | H2: 27405 | I2: 43403 | J2: N/A | K2: Customer Service | L2: Help Desk Technician | M2: 66787 | N2: =IF(J2="","Active","Terminated") -> Terminated | O2: Satisfactory
A3: 00-10006914 | B3: Ethan | C3: Case | D3: Male | E3: Michigan | F3: Detroit | G3: High School | H3: 29488 | I3: 44846 | J3: N/A | K3: Operations | L3: Inventory Specialist | M3: 63874 | N3: =IF(J3="","Active","Terminated") -> Terminated | O3: Needs Improvement
A4: 00-10008169 | B4: Barbara | C4: Blair | D4: Male | E4: Michigan | F4: Warren | G4: Bachelor | H4: 21759 | I4: 44888 | J4: N/A | K4: Operations | L4: Operations Analyst | M4: 88579 | N4: =IF(J4="","Active","Terminated") -> Terminated | O4: Good
A5: 00-10012470 | B5: Amy | C5: Davidson | D5: Female | E5: Michigan | F5: Grand Rapids | G5: Bachelor | H5: 32562 | I5: 43753 | J5: N/A | K5: Finance | L5: Accountant | M5: 62543 | N5: =IF(J5="","Active","Terminated") -> Terminated | O5: Good
A6: 00-10017850 | B6: Ricky | C6: Serrano | D6: Male | E6: New York | F6: New York City | G6: Bachelor | H6: 36787 | I6: 42650 | J6: N/A | K6: Sales | L6: Sales Specialist | M6: 92123 | N6: =IF(J6="","Active","Terminated") -> Terminated | O6: Good
A7: 00-10033114 | B7: Kathryn | C7: Scott | D7: Male | E7: New York | F7: New York City | G7: Bachelor | H7: 37077 | I7: 42990 | J7: N/A | K7: Operations | L7: Logistics Coordinator | M7: 64807 | N7: =IF(J7="","Active","Terminated") -> Terminated | O7: Good
A8: 00-10047461 | B8: Steven | C8: Armstrong | D8: Female | E8: Illinois | F8: Naperville | G8: Bachelor | H8: 33952 | I8: 42590 | J8: N/A | K8: Finance | L8: Accountant | M8: 70778 | N8: =IF(J8="","Active","Terminated") -> Terminated | O8: Satisfactory
A9: 00-10076576 | B9: Erica | C9: Kelly | D9: Male | E9: New York | F9: Buffalo | G9: Bachelor | H9: 36317 | I9: 43833 | J9: N/A | K9: Operations | L9: Inventory Specialist | M9: 63824 | N9: =IF(J9="","Active","Terminated") -> Terminated | O9: Excellent
A10: 00-10076959 | B10: Mark | C10: Stewart | D10: Male | E10: New York | F10: Buffalo | G10: Bachelor | H10: 23131 | I10: 42825 | J10: N/A | K10: Marketing | L10: Marketing Coordinator | M10: 76850 | N10: =IF(J10="","Active","Terminated") -> Terminated | O10: Satisfactory
A11: 00-10080009 | B11: Gabrielle | C11: Crane | D11: Female | E11: New York | F11: Buffalo | G11: Bachelor | H11: 28399 | I11: 44935 | J11: N/A | K11: Sales | L11: Sales Representative | M11: 59328 | N11: =IF(J11="","Active","Terminated") -> Terminated | O11: Good
A12: 00-10113173 | B12: Carol | C12: Smith | D12: Female | E12: Michigan | F12: Detroit | G12: High School | H12: 31919 | I12: 44764 | J12: N/A | K12: Marketing | L12: Content Creator | M12: 60340 | N12: =IF(J12="","Active","Terminated") -> Terminated | O12: Satisfactory
A13: 00-10113880 | B13: Brad | C13: Hobbs | D13: Male | E13: New York | F13: Buffalo | G13: High School | H13: 31651 | I13: 42815 | J13: N/A | K13: Marketing | L13: Content Creator | M13: 54733 | N13: =IF(J13="","Active","Terminated") -> Terminated | O13: Good
... A22: 00-10202363 | B22: Michelle | C22: Lang | D22: Female | E22: New York | F22: New York City | G22: Bachelor | H22: 35150 | I22: 44672 | J22: N/A | K22: Sales | L22: Sales Representative | M22: 52278 | N22: =IF(J22="","Active","Terminated") -> Terminated | O22: Satisfactory
A23: 00-10209961 | B23: Daniel | C23: Graham | D23: Male | E23: New York | F23: New York City | G23: Bachelor | H23: 32658 | I23: 44352 | J23: 44532 | K23: Sales | L23: Sales Representative | M23: 64892 | N23: =IF(J23="","Active","Terminated") -> Terminated | O23: Good
A24: 00-10213612 | B24: Gabriel | C24: Harris | D24: Female | E24: New York | F24: New York City | G24: Bachelor | H24: 27813 | I24: 44477 | J24: N/A | K24: Operations | L24: Operations Analyst | M24: 60624 | N24: =IF(J24="","Active","Terminated") -> Terminated | O24: Satisfactory
A25: 00-10225283 | B25: Ryan | C25: Long | D25: Female | E25: New York | F25: Rochester | G25: High School | H25: 26606 | I25: 43115 | J25: N/A | K25: Operations | L25: Inventory Specialist | M25: 59233 | N25: =IF(J25="","Active","Terminated") -> Terminated | O25: Satisfactory
A26: 00-10256489 | B26: Sue | C26: Howe | D26: Female | E26: New York | F26: Buffalo | G26: Bachelor | H26: 29633 | I26: 45418 | J26: N/A | K26: Sales | L26: Sales Representative | M26: 68287 | N26: =IF(J26="","Active","Terminated") -> Terminated | O26: Satisfactory
A27: 00-10261534 | B27: Kevin | C27: Potter | D27: Female | E27: Ohio | F27: Cincinnati | G27: Bachelor | H27: 28211 | I27: 45467 | J27: N/A | K27: Operations | L27: Logistics Coordinator | M27: 62856 | N27: =IF(J27="","Active","Terminated") -> Terminated | O27: Good
A28: 00-10270663 | B28: William | C28: Wilson | D28: Female | E28: New York | F28: New York City | G28: Bachelor | H28: 30745 | I28: 42958 | J28: N/A | K28: Sales | L28: Sales Representative | M28: 57572 | N28: =IF(J28="","Active","Terminated") -> Terminated | O28: Excellent
A29: 00-10274812 | B29: Heather | C29: Madden | D29: Female | E29: New York | F29: Rochester | G29: Bachelor | H29: 26390 | I29: 44484 | J29: N/A | K29: Operations | L29: Inventory Specialist | M29: 67571 | N29: =IF(J29="","Active","Terminated") -> Terminated | O29: Good
A30: 00-10279945 | B30: Karen | C30: Stephens | D30: Female | E30: New York | F30: Rochester | G30: High School | H30: 22399 | I30: 42708 | J30: N/A | K30: HR | L30: Recruiter | M30: 70509 | N30: =IF(J30="","Active","Terminated") -> Terminated | O30: Satisfactory
A31: 00-10289289 | B31: Robert | C31: Shields | D31: Female | E31: New York | F31: New York City | G31: Bachelor | H31: 28700 | I31: 45313 | J31: 45493 | K31: Customer Service | L31: Help Desk Technician | M31: 61403 | N31: =IF(J31="","Active","Terminated") -> Terminated | O31: Good
A32: 00-10299883 | B32: Shawn | C32: Sanchez | D32: Male | E32: New York | F32: Rochester | G32: Bachelor | H32: 25711 | I32: 44686 | J32: N/A | K32: Marketing | L32: Marketing Coordinator | M32: 69918 | N32: =IF(J32="","Active","Terminated") -> Terminated | O32: Good
A33: 00-10302186 | B33: Amy | C33: Davis | D33: Female | E33: New York | F33: Buffalo | G33: High School | H33: 26766 | I33: 43181 | J33: N/A | K33: Operations | L33: Inventory Specialist | M33: 65488 | N33: =IF(J33="","Active","Terminated") -> Terminated | O33: Satisfactory
A34: 00-10308646 | B34: Kristy | C34: Wilson | D34: Female | E34: New York | F34: Rochester | G34: High School | H34: 32660 | I34: 42883 | J34: N/A | K34: Marketing | L34: Content Creator | M34: 59706 | N34: =IF(J34="","Active","Terminated") -> Terminated | O34: Satisfactory
A35: 00-10329821 | B35: Mercedes | C35: Patterson | D35: Male | E35: New York | F35: New York City | G35: Bachelor | H35: 36415 | I35: 44681 | J35: N/A | K35: Operations | L35: Inventory Specialist | M35: 57722 | N35: =IF(J35="","Active","Terminated") -> Terminated | O35: Good
A36: 00-10331931 | B36: Gabriella | C36: Abbott | D36: Male | E36: New York | F36: New York City | G36: PhD | H36: 32530 | I36: 42989 | J36: 43168 | K36: Sales | L36: Sales Specialist | M36: 78790 | N36: =IF(J36="","Active","Terminated") -> Terminated | O36: Excellent
A37: 00-10332878 | B37: William | C37: Potter | D37: Female | E37: Virginia | F37: Norfolk | G37: Bachelor | H37: 36767 | I37: 45585 | J37: N/A | K37: Operations | L37: Logistics Coordinator | M37: 55750 | N37: =IF(J37="","Active","Terminated") -> Terminated | O37: Good
A38: 00-10333912 | B38: Angela | C38: Perry | D38: Male | E38: Illinois | F38: Naperville | G38: Bachelor | H38: 26067 | I38: 43437 | J38: N/A | K38: Operations | L38: Logistics Coordinator | M38: 62346 | N38: =IF(J38="","Active","Terminated") -> Terminated | O38: Satisfactory
A39: 00-10338423 | B39: Amanda | C39: Bradley | D39: Male | E39: West Virginia | F39: Charleston | G39: PhD | H39: 35327 | I39: 45168 | J39: N/A | K39: Sales | L39: Sales Specialist | M39: 78128 | N39: =IF(J39="","Active","Terminated") -> Terminated | O39: Good
A40: 00-10339260 | B40: Diana | C40: Jones | D40: Female | E40: New York | F40: Rochester | G40: Bachelor | H40: 26885 | I40: 43815 | J40: N/A | K40: Marketing | L40: SEO Specialist | M40: 61326 | N40: =IF(J40="","Active","Terminated") -> Terminated | O40: Good
A41: 00-10355692 | B41: Samuel | C41: Ayala | D41: Female | E41: New York | F41: Buffalo | G41: High School | H41: 22740 | I41: 42301 | J41: N/A | K41: Operations | L41: Inventory Specialist | M41: 56998 | N41: =IF(J41="","Active","Terminated") -> Terminated | O41: Excellent
A42: 00-10358749 | B42: Kimberly | C42: Mercado | D42: Female | E42: New York | F42: New York City | G42: High School | H42: 28585 | I42: 45246 | J42: N/A | K42: Marketing | L42: Content Creator | M42: 59294 | N42: =IF(J42="","Active","Terminated") -> Terminated | O42: Satisfactory
A43: 00-10392185 | B43: Sherry | C43: Carpenter | D43: Male | E43: North Carolina | F43: Raleigh | G43: High School | H43: 28486 | I43: 42438 | J43: N/A | K43: Customer Service | L43: Customer Service Representative | M43: 59847 | N43: =IF(J43="","Active","Terminated") -> Terminated | O43: Needs Improvement
A44: 00-10403216 | B44: Aaron | C44: Horton | D44: Female | E44: New York | F44: Rochester | G44: High School | H44: 34594 | I44: 43098 | J44: N/A | K44: Customer Service | L44: Support Specialist | M44: 60852 | N44: =IF(J44="","Active","Terminated") -> Terminated | O44: Satisfactory
A45: 00-10404729 | B45: John | C45: Grimes | D45: Female | E45: Virginia | F45: Virginia Beach | G45: Bachelor | H45: 29781 | I45: 44624 | J45: 44804 | K45: Customer Service | L45: Help Desk Technician | M45: 58407 | N45: =IF(J45="","Active","Terminated") -> Terminated | O45: Good
A46: 00-10409797 | B46: Gloria | C46: Hale | D46: Male | E46: Michigan | F46: Grand Rapids | G46: High School | H46: 35565 | I46: 43455 | J46: N/A | K46: Customer Service | L46: Help Desk Technician | M46: 57046 | N46: =IF(J46="","Active","Terminated") -> Terminated | O46: Needs Improvement
A47: 00-10412827 | B47: Savannah | C47: Howard | D47: Male | E47: North Carolina | F47: Raleigh | G47: High School | H47: 30977 | I47: 43730 | J47: N/A | K47: Operations | L47: Inventory Specialist | M47: 63356 | N47: =IF(J47="","Active","Terminated") -> Terminated | O47: Satisfactory
A48: 00-10432769 | B48: Robin | C48: Gutierrez | D48: Female | E48: New York | F48: Buffalo | G48: Bachelor | H48: 33867 | I48: 43419 | J48: N/A | K48: Customer Service | L48: Customer Service Representative | M48: 60621 | N48: =IF(J48="","Active","Terminated") -> Terminated | O48: Satisfactory
A49: 00-10446705 | B49: Michelle | C49: Johnson | D49: Female | E49: New York | F49: Buffalo | G49: Bachelor | H49: 37372 | I49: 45446 | J49: N/A | K49: Customer Service | L49: Support Specialist | M49: 54933 | N49: =IF(J49="","Active","Terminated") -> Terminated | O49: Good
A50: 00-10457051 | B50: Christopher | C50: Pitts | D50: Female | E50: New York | F50: Buffalo | G50: Bachelor | H50: 23453 | I50: 42380 | J50: N/A | K50: Sales | L50: Sales Representative | M50: 61979 | N50: =IF(J50="","Active","Terminated") -> Terminated | O50: Good
A51: 00-10460418 | B51: Barbara | C51: Stevens | D51: Female | E51: Michigan | F51: Grand Rapids | G51: Bachelor | H51: 32104 | I51: 45570 | J51: N/A | K51: Marketing | L51: Marketing Coordinator | M51: 64471 | N51: =IF(J51="","Active","Terminated") -> Terminated | O51: Needs Improvement
A52: 00-10464811 | B52: Martha | C52: Williams | D52: Male | E52: New York | F52: Buffalo | G52: Bachelor | H52: 31172 | I52: 43634 | J52: N/A | K52: Sales | L52: Sales Representative | M52: 63604 | N52: =IF(J52="","Active","Terminated") -> Terminated | O52: Good
A53: 00-10466177 | B53: Joseph | C53: Diaz | D53: Female | E53: Michigan | F53: Warren | G53: Bachelor | H53: 33369 | I53: 44718 | J53: 44898 | K53: Finance | L53: Accountant | M53: 53179 | N53: =IF(J53="","Active","Terminated") -> Terminated | O53: Satisfactory
A54: 00-10470877 | B54: Paul | C54: Day | D54: Male | E54: New York | F54: Rochester | G54: Master | H54: 22624 | I54: 43178 | J54: N/A | K54: HR | L54: HR Coordinator | M54: 54969 | N54: =IF(J54="","Active","Terminated") -> Terminated | O54: Good
A55: 00-10475894 | B55: Joseph | C55: Anderson | D55: Male | E55: New York | F55: New York City | G55: Bachelor | H55: 30308 | I55: 43351 | J55: 43662 | K55: IT | L55: Software Developer | M55: 89897 | N55: =IF(J55="","Active","Terminated") -> Terminated | O55: Good
A56: 00-10476674 | B56: Jeffrey | C56: Roach | D56: Female | E56: New York | F56: Rochester | G56: Bachelor | H56: 35978 | I56: 45062 | J56: N/A | K56: Marketing | L56: Marketing Coordinator | M56: 70313 | N56: =IF(J56="","Active","Terminated") -> Terminated | O56: Good
A57: 00-10486734 | B57: Scott | C57: Riddle | D57: Female | E57: Virginia | F57: Virginia Beach | G57: PhD | H57: 34891 | I57: 42475 | J57: N/A | K57: Finance | L57: Financial Analyst | M57: 104437 | N57: =IF(J57="","Active","Terminated") -> Terminated | O57: Satisfactory
A58: 00-10503430 | B58: Joshua | C58: Austin | D58: Male | E58: New York | F58: New York City | G58: High School | H58: 30332 | I58: 45243 | J58: N/A | K58: Customer Service | L58: Customer Service Representative | M58: 66995 | N58: =IF(J58="","Active","Terminated") -> Terminated | O58: Good
A59: 00-10515548 | B59: Mandy | C59: Mason | D59: Male | E59: New York | F59: New York City | G59: Bachelor | H59: 33215 | I59: 43749 | J59: N/A | K59: Operations | L59: Logistics Coordinator | M59: 69085 | N59: =IF(J59="","Active","Terminated") -> Terminated | O59: Good
A60: 00-10538139 | B60: Michael | C60: Schaefer | D60: Female | E60: New York | F60: Rochester | G60: Bachelor | H60: 26345 | I60: 42461 | J60: N/A | K60: Sales | L60: Sales Representative | M60: 73674 | N60: =IF(J60="","Active","Terminated") -> Terminated | O60: Satisfactory
A61: 00-10551617 | B61: Alan | C61: Weeks | D61: Male | E61: New York | F61: New York City | G61: Master | H61: 29916 | I61: 43394 | J61: N/A | K61: Sales | L61: Sales Consultant | M61: 68761 | N61: =IF(J61="","Active","Terminated") -> Terminated | O61: Good
A62: 00-10573904 | B62: Christopher | C62: Martin | D62: Male | E62: New York | F62: New York City | G62: Bachelor | H62: 32539 | I62: 44850 | J62: N/A | K62: Operations | L62: Logistics Coordinator | M62: 69563 | N62: =IF(J62="","Active","Terminated") -> Terminated | O62: Excellent
A63: 00-10578224 | B63: Richard | C63: Todd | D63: Male | E63: New York | F63: Rochester | G63: Bachelor | H63: 36449 | I63: 42846 | J63: N/A | K63: Operations | L63: Inventory Specialist | M63: 66275 | N63: =IF(J63="","Active","Terminated") -> Terminated | O63: Satisfactory
A64: 00-10605250 | B64: Karen | C64: Martin | D64: Female | E64: Pennsylvania | F64: Allentown | G64: Master | H64: 33750 | I64: 43851 | J64: N/A | K64: Operations | L64: Operations Analyst | M64: 60271 | N64: =IF(J64="","Active","Terminated") -> Terminated | O64: Good
A65: 00-10614102 | B65: Matthew | C65: Combs | D65: Female | E65: New York | F65: Rochester | G65: PhD | H65: 34112 | I65: 45517 | J65: N/A | K65: Sales | L65: Sales Specialist | M65: 66553 | N65: =IF(J65="","Active","Terminated") -> Terminated | O65: Needs Improvement
A66: 00-10617870 | B66: Erin | C66: Ramos | D66: Female | E66: New York | F66: Buffalo | G66: Bachelor | H66: 31413 | I66: 45370 | J66: N/A | K66: Operations | L66: Operations Manager | M66: 95684 | N66: =IF(J66="","Active","Terminated") -> Terminated | O66: Good
A67: 00-10625592 | B67: Sarah | C67: Bauer | D67: Female | E67: Virginia | F67: Norfolk | G67: Bachelor | H67: 29200 | I67: 43224 | J67: N/A | K67: Sales | L67: Sales Specialist | M67: 69113 | N67: =IF(J67="","Active","Terminated") -> Terminated | O67: Satisfactory
... A72: 00-10691813 | B72: Robert | C72: Woodard | D72: Female | E72: New York | F72: Buffalo | G72: High School | H72: 23506 | I72: 43374 | J72: N/A | K72: Customer Service | L72: Support Specialist | M72: 61344 | N72: =IF(J72="","Active","Terminated") -> Terminated | O72: Satisfactory
A73: 00-10697290 | B73: Christina | C73: Robinson | D73: Female | E73: Pennsylvania | F73: Pittsburgh | G73: Bachelor | H73: 29199 | I73: 45343 | J73: 45523 | K73: Customer Service | L73: Customer Service Representative | M73: 55001 | N73: =IF(J73="","Active","Terminated") -> Terminated | O73: Good
A74: 00-10753570 | B74: Carolyn | C74: Robinson | D74: Female | E74: New York | F74: New York City | G74: Bachelor | H74: 29386 | I74: 43912 | J74: N/A | K74: Customer Service | L74: Support Specialist | M74: 63693 | N74: =IF(J74="","Active","Terminated") -> Terminated | O74: Satisfactory
A75: 00-10764034 | B75: Kenneth | C75: Wallace | D75: Male | E75: New York | F75: Rochester | G75: Bachelor | H75: 34400 | I75: 43406 | J75: N/A | K75: Marketing | L75: Marketing Coordinator | M75: 76788 | N75: =IF(J75="","Active","Terminated") -> Terminated | O75: Needs Improvement
A76: 00-10776989 | B76: Kristi | C76: Wade | D76: Male | E76: New York | F76: Rochester | G76: High School | H76: 33021 | I76: 44919 | J76: N/A | K76: Operations | L76: Inventory Specialist | M76: 59332 | N76: =IF(J76="","Active","Terminated") -> Terminated | O76: Satisfactory
A77: 00-10784416 | B77: Amy | C77: Escobar | D77: Male | E77: Ohio | F77: Columbus | G77: High School | H77: 32465 | I77: 44817 | J77: N/A | K77: Customer Service | L77: Customer Service Representative | M77: 64929 | N77: =IF(J77="","Active","Terminated") -> Terminated | O77: Good
A78: 00-10791740 | B78: Andrew | C78: Deleon | D78: Female | E78: North Carolina | F78: Raleigh | G78: Bachelor | H78: 36083 | I78: 44495 | J78: N/A | K78: Operations | L78: Inventory Specialist | M78: 57924 | N78: =IF(J78="","Active","Terminated") -> Terminated | O78: Good
A79: 00-10808854 | B79: Rachel | C79: Glover | D79: Male | E79: Illinois | F79: Aurora | G79: Bachelor | H79: 31205 | I79: 43450 | J79: N/A | K79: IT | L79: Software Developer | M79: 86885 | N79: =IF(J79="","Active","Terminated") -> Terminated | O79: Good
A80: 00-10842074 | B80: Tyler | C80: Rodriguez | D80: Male | E80: New York | F80: New York City | G80: High School | H80: 30879 | I80: 44387 | J80: N/A | K80: IT | L80: IT Support Specialist | M80: 63937 | N80: =IF(J80="","Active","Terminated") -> Terminated | O80: Good
A81: 00-10856024 | B81: Timothy | C81: Phillips | D81: Male | E81: Virginia | F81: Richmond | G81: Bachelor | H81: 37375 | I81: 43457 | J81: 43637 | K81: Operations | L81: Inventory Specialist | M81: 61322 | N81: =IF(J81="","Active","Terminated") -> Terminated | O81: Excellent
A82: 00-10865811 | B82: Debbie | C82: Klein | D82: Female | E82: New York | F82: Rochester | G82: Bachelor | H82: 25616 | I82: 45145 | J82: N/A | K82: Marketing | L82: Content Creator | M82: 57329 | N82: =IF(J82="","Active","Terminated") -> Terminated | O82: Satisfactory
A83: 00-10874735 | B83: David | C83: Santiago | D83: Female | E83: Michigan | F83: Warren | G83: Bachelor | H83: 31413 | I83: 43280 | J83: N/A | K83: IT | L83: Software Developer | M83: 82070 | N83: =IF(J83="","Active","Terminated") -> Terminated | O83: Satisfactory
A84: 00-10881653 | B84: Rachel | C84: Miller | D84: Male | E84: Illinois | F84: Aurora | G84: Bachelor | H84: 23103 | I84: 43198 | J84: N/A | K84: Customer Service | L84: Help Desk Technician | M84: 64295 | N84: =IF(J84="","Active","Terminated") -> Terminated | O84: Good
A85: 00-10884169 | B85: Elizabeth | C85: Spence | D85: Female | E85: New York | F85: New York City | G85: Bachelor | H85: 24809 | I85: 42793 | J85: N/A | K85: Sales | L85: Sales Representative | M85: 69161 | N85: =IF(J85="","Active","Terminated") -> Terminated | O85: Good
A86: 00-10902666 | B86: Justin | C86: Martin | D86: Male | E86: New York | F86: Rochester | G86: Bachelor | H86: 23523 | I86: 43367 | J86: N/A | K86: Operations | L86: Logistics Coordinator | M86: 71715 | N86: =IF(J86="","Active","Terminated") -> Terminated | O86: Good
A87: 00-10909370 | B87: Cody | C87: Arnold | D87: Male | E87: New York | F87: New York City | G87: Bachelor | H87: 27287 | I87: 45489 | J87: N/A | K87: Operations | L87: Inventory Specialist | M87: 63956 | N87: =IF(J87="","Active","Terminated") -> Terminated | O87: Good
A88: 00-10923862 | B88: Gregory | C88: Baker | D88: Female | E88: New York | F88: Rochester | G88: Bachelor | H88: 29575 | I88: 44591 | J88: N/A | K88: Operations | L88: Logistics Coordinator | M88: 55222 | N88: =IF(J88="","Active","Terminated") -> Terminated | O88: Good
A89: 00-10933716 | B89: Jennifer | C89: Shah | D89: Male | E89: New York | F89: Buffalo | G89: Master | H89: 30057 | I89: 43414 | J89: N/A | K89: Operations | L89: Operations Analyst | M89: 73378 | N89: =IF(J89="","Active","Terminated") -> Terminated | O89: Satisfactory
A90: 00-10954835 | B90: Brandon | C90: Christian | D90: Male | E90: New York | F90: New York City | G90: High School | H90: 32372 | I90: 44088 | J90: N/A | K90: Customer Service | L90: Help Desk Technician | M90: 59535 | N90: =IF(J90="","Active","Terminated") -> Terminated | O90: Needs Improvement
A91: 00-10954878 | B91: Anita | C91: Wagner | D91: Male | E91: New York | F91: Rochester | G91: Master | H91: 37704 | I91: 44376 | J91: N/A | K91: IT | L91: IT Manager | M91: 121086 | N91: =IF(J91="","Active","Terminated") -> Terminated | O91: Excellent
A92: 00-10959975 | B92: Lori | C92: Daniels | D92: Female | E92: Pennsylvania | F92: Philadelphia | G92: Bachelor | H92: 37328 | I92: 43170 | J92: N/A | K92: Sales | L92: Sales Representative | M92: 58267 | N92: =IF(J92="","Active","Terminated") -> Terminated | O92: Excellent
A93: 00-10965569 | B93: Deborah | C93: Murphy | D93: Male | E93: North Carolina | F93: Greensboro | G93: Bachelor | H93: 33203 | I93: 43448 | J93: N/A | K93: Operations | L93: Inventory Specialist | M93: 67221 | N93: =IF(J93="","Active","Terminated") -> Terminated | O93: Good
... A152: 00-11516293 | B152: Lawrence | C152: Delgado | D152: Female | E152: New York | F152: New York City | G152: Bachelor | H152: 33896 | I152: 44472 | J152: N/A | K152: Operations | L152: Logistics Coordinator | M152: 58636 | N152: =IF(J152="","Active","Terminated") -> Terminated | O152: Excellent
A153: 00-11523452 | B153: Kristi | C153: Diaz | D153: Female | E153: New York | F153: New York City | G153: Master | H153: 30789 | I153: 43097 | J153: 44373 | K153: IT | L153: Software Developer | M153: 94351 | N153: =IF(J153="","Active","Terminated") -> Terminated | O153: Good
A154: 00-11524245 | B154: Donna | C154: Mccoy | D154: Female | E154: New York | F154: Rochester | G154: PhD | H154: 32504 | I154: 45183 | J154: N/A | K154: Sales | L154: Sales Specialist | M154: 82055 | N154: =IF(J154="","Active","Terminated") -> Terminated | O154: Satisfactory
A155: 00-11524247 | B155: Michael | C155: Hudson | D155: Male | E155: New York | F155: New York City | G155: Bachelor | H155: 21827 | I155: 43248 | J155: N/A | K155: Customer Service | L155: Help Desk Technician | M155: 89858 | N155: =IF(J155="","Active","Terminated") -> Terminated | O155: Excellent
A156: 00-11529494 | B156: Amy | C156: Anderson | D156: Male | E156: New York | F156: New York City | G156: Bachelor | H156: 25902 | I156: 43067 | J156: 44941 | K156: Operations | L156: Inventory Specialist | M156: 66416 | N156: =IF(J156="","Active","Terminated") -> Terminated | O156: Good
A157: 00-11536077 | B157: Phillip | C157: Hernandez | D157: Male | E157: New York | F157: Rochester | G157: Bachelor | H157: 26380 | I157: 45148 | J157: N/A | K157: Operations | L157: Inventory Specialist | M157: 62376 | N157: =IF(J157="","Active","Terminated") -> Terminated | O157: Good
A158: 00-11558972 | B158: Anna | C158: Brown | D158: Female | E158: Ohio | F158: Cleveland | G158: PhD | H158: 27116 | I158: 42933 | J158: N/A | K158: Sales | L158: Sales Specialist | M158: 95430 | N158: =IF(J158="","Active","Terminated") -> Terminated | O158: Satisfactory
A159: 00-11577154 | B159: Roberta | C159: Rodgers | D159: Male | E159: Michigan | F159: Detroit | G159: Bachelor | H159: 29001 | I159: 43699 | J159: N/A | K159: Operations | L159: Inventory Specialist | M159: 70889 | N159: =IF(J159="","Active","Terminated") -> Terminated | O159: Good
A160: 00-11582229 | B160: Andrew | C160: Byrd | D160: Female | E160: New York | F160: New York City | G160: High School | H160: 36684 | I160: 44344 | J160: N/A | K160: Operations | L160: Inventory Specialist | M160: 54981 | N160: =IF(J160="","Active","Terminated") -> Terminated | O160: Needs Improvement
A161: 00-11586450 | B161: Nicole | C161: Gordon | D161: Male | E161: New York | F161: New York City | G161: Bachelor | H161: 29530 | I161: 44711 | J161: N/A | K161: Operations | L161: Logistics Coordinator | M161: 70196 | N161: =IF(J161="","Active","Terminated") -> Terminated | O161: Needs Improvement
A162: 00-11590610 | B162: Eric | C162: Delgado | D162: Female | E162: New York | F162: New York City | G162: Bachelor | H162: 31644 | I162: 42347 | J162: 43705 | K162: Sales | L162: Sales Representative | M162: 61011 | N162: =IF(J162="","Active","Terminated") -> Terminated | O162: Satisfactory
A163: 00-11604831 | B163: Brittany | C163: Powers | D163: Male | E163: New York | F163: New York City | G163: Bachelor | H163: 35310 | I163: 42491 | J163: 44560 | K163: Customer Service | L163: Help Desk Technician | M163: 92489 | N163: =IF(J163="","Active","Terminated") -> Terminated | O163: Good
A164: 00-11619567 | B164: Robert | C164: Mcknight | D164: Male | E164: New York | F164: Buffalo | G164: Master | H164: 26958 | I164: 42856 | J164: N/A | K164: Operations | L164: Operations Analyst | M164: 57267 | N164: =IF(J164="","Active","Terminated") -> Terminated | O164: Excellent
A165: 00-11620224 | B165: Christina | C165: Caldwell | D165: Female | E165: New York | F165: New York City | G165: Bachelor | H165: 27424 | I165: 43081 | J165: N/A | K165: Sales | L165: Sales Representative | M165: 73580 | N165: =IF(J165="","Active","Terminated") -> Terminated | O165: Excellent
A166: 00-11626011 | B166: Jessica | C166: Thomas | D166: Male | E166: New York | F166: New York City | G166: Bachelor | H166: 31232 | I166: 45450 | J166: N/A | K166: Sales | L166: Sales Representative | M166: 84223 | N166: =IF(J166="","Active","Terminated") -> Terminated | O166: Satisfactory
A167: 00-11632815 | B167: Jamie | C167: Hernandez | D167: Female | E167: Michigan | F167: Detroit | G167: Master | H167: 30655 | I167: 42606 | J167: N/A | K167: Operations | L167: Operations Analyst | M167: 70204 | N167: =IF(J167="","Active","Terminated") -> Terminated | O167: Satisfactory
A168: 00-11638103 | B168: Brandi | C168: Buckley | D168: Male | E168: New York | F168: New York City | G168: Master | H168: 23615 | I168: 42843 | J168: N/A | K168: Operations | L168: Operations Analyst | M168: 69918 | N168: =IF(J168="","Active","Terminated") -> Terminated | O168: Good
A169: 00-11640743 | B169: Michael | C169: Johnson | D169: Female | E169: New York | F169: Rochester | G169: Bachelor | H169: 38051 | I169: 42805 | J169: N/A | K169: Sales | L169: Sales Representative | M169: 59874 | N169: =IF(J169="","Active","Terminated") -> Terminated | O169: Excellent
A170: 00-11658976 | B170: Richard | C170: White | D170: Male | E170: Michigan | F170: Detroit | G170: Bachelor | H170: 32989 | I170: 43026 | J170: N/A | K170: IT | L170: Software Developer | M170: 110431 | N170: =IF(J170="","Active","Terminated") -> Terminated | O170: Excellent
...

Sheet COUNT IF,SUMIFS&AVG IFS
B1: Department | C1: HEAD COUNT | D1: TOTAL SALARY | E1: AVG SALARY
B2: Customer Service | C2: =COUNTIF(STAFF!K:K,B2) -> 1673 | D2: =SUMIF(STAFF!K:K,B2,STAFF!M:M) -> 110146520 | E2: =AVERAGEIF(STAFF!K:K,B2,STAFF!M:M) -> 65837.729
B3: Operations | C3: =COUNTIF(STAFF!K:K,B3) -> 2718 | D3: =SUMIF(STAFF!K:K,B3,STAFF!M:M) -> 177757880 | E3: =AVERAGEIF(STAFF!K:K,B3,STAFF!M:M) -> 65400.25
B4: Finance | C4: =COUNTIF(STAFF!K:K,B4) -> 452 | D4: =SUMIF(STAFF!K:K,B4,STAFF!M:M) -> 34555917 | E4: =AVERAGEIF(STAFF!K:K,B4,STAFF!M:M) -> 76451.144
B5: Sales | C5: =COUNTIF(STAFF!K:K,B5) -> 1835 | D5: =SUMIF(STAFF!K:K,B5,STAFF!M:M) -> 139836079 | E5: =AVERAGEIF(STAFF!K:K,B5,STAFF!M:M) -> 76204.948
B6: Marketing | C6: =COUNTIF(STAFF!K:K,B6) -> 718 | D6: =SUMIF(STAFF!K:K,B6,STAFF!M:M) -> 48579179 | E6: =AVERAGEIF(STAFF!K:K,B6,STAFF!M:M) -> 67659.024
B7: HR | C7: =COUNTIF(STAFF!K:K,B7) -> 172 | D7: =SUMIF(STAFF!K:K,B7,STAFF!M:M) -> 11032946 | E7: =AVERAGEIF(STAFF!K:K,B7,STAFF!M:M) -> 64145.035
B8: IT | C8: =COUNTIF(STAFF!K:K,B8) -> 1382 | D8: =SUMIF(STAFF!K:K,B8,STAFF!M:M) -> 113221190 | E8: =AVERAGEIF(STAFF!K:K,B8,STAFF!M:M) -> 81925.608

Sheet FILTER FOR>120000,FEMALE 
F1: 120000
B3: {=_xlfn._xlws.FILTER(STAFF!A:M,STAFF!M:M>F1)} -> Employee_ID | C3: First Name | D3: Last Name | E3: Gender | F3: State | G3: City | H3: Education Level | I3: Birthdate | J3: Hiredate | K3: Termdate | L3: Department | M3: Job Title | N3: Salary | Q3: {=_xlfn._xlws.FILTER(STAFF!A:M,(STAFF!D:D="Female")*(STAFF!M:M>F1))} -> 00-11145938 | R3: Holly | S3: Gray | T3: Female | U3: New York | V3: New York City | W3: Master | X3: 36084 | Y3: 42983 | Z3: N/A | AA3: IT | AB3: IT Manager | AC3: 133425
B4: 00-10954878 | C4: Anita | D4: Wagner | E4: Male | F4: New York | G4: Rochester | H4: Master | I4: 37704 | J4: 44376 | K4: N/A | L4: IT | M4: IT Manager | N4: 121086 | Q4: 00-15537346 | R4: Jose | S4: Smith | T4: Female | U4: New York | V4: Buffalo | W4: PhD | X4: 22499 | Y4: 44869 | Z4: N/A | AA4: Finance | AB4: Finance Manager | AC4: 141543
B5: 00-11145938 | C5: Holly | D5: Gray | E5: Female | F5: New York | G5: New York City | H5: Master | I5: 36084 | J5: 42983 | K5: N/A | L5: IT | M5: IT Manager | N5: 133425 | Q5: 00-17850078 | R5: Dawn | S5: Hernandez | T5: Female | U5: New York | V5: Rochester | W5: Master | X5: 26012 | Y5: 43103 | Z5: N/A | AA5: Sales | AB5: Sales Manager | AC5: 125480
B6: 00-12738346 | C6: Kristen | D6: Green | E6: Male | F6: New York | G6: Rochester | H6: PhD | I6: 23310 | J6: 44806 | K6: N/A | L6: IT | M6: IT Manager | N6: 125068 | Q6: 00-23430634 | R6: Vincent | S6: Ross | T6: Female | U6: New York | V6: Rochester | W6: PhD | X6: 34332 | Y6: 43122 | Z6: N/A | AA6: Sales | AB6: Sales Manager | AC6: 133039
B7: 00-14237322 | C7: Kenneth | D7: Griffin | E7: Male | F7: New York | G7: New York City | H7: Master | I7: 32976 | J7: 44109 | K7: 44289 | L7: IT | M7: IT Manager | N7: 131494 | Q7: 00-30370571 | R7: Rebecca | S7: Estes | T7: Female | U7: Michigan | V7: Grand Rapids | W7: PhD | X7: 27872 | Y7: 45108 | Z7: N/A | AA7: Sales | AB7: Sales Manager | AC7: 127318
B8: 00-15537346 | C8: Jose | D8: Smith | E8: Female | F8: New York | G8: Buffalo | H8: PhD | I8: 22499 | J8: 44869 | K8: N/A | L8: Finance | M8: Finance Manager | N8: 141543 | Q8: 00-34077528 | R8: Gregory | S8: Wood | T8: Female | U8: New York | V8: Rochester | W8: Master | X8: 31675 | Y8: 43007 | Z8: N/A | AA8: Finance | AB8: Finance Manager | AC8: 132723
B9: 00-17850078 | C9: Dawn | D9: Hernandez | E9: Female | F9: New York | G9: Rochester | H9: Master | I9: 26012 | J9: 43103 | K9: N/A | L9: Sales | M9: Sales Manager | N9: 125480 | Q9: 00-42521351 | R9: Theresa | S9: Galloway | T9: Female | U9: New York | V9: Rochester | W9: PhD | X9: 21954 | Y9: 44087 | Z9: N/A | AA9: Sales | AB9: Sales Manager | AC9: 122906
B10: 00-18045780 | C10: Rodney | D10: Mosley | E10: Male | F10: Michigan | G10: Detroit | H10: Bachelor | I10: 25428 | J10: 44981 | K10: N/A | L10: IT | M10: Software Developer | N10: 120359 | Q10: 00-44042835 | R10: Raymond | S10: Lopez | T10: Female | U10: New York | V10: Buffalo | W10: PhD | X10: 34275 | Y10: 43708 | Z10: N/A | AA10: IT | AB10: IT Manager | AC10: 133044
B11: 00-23430634 | C11: Vincent | D11: Ross | E11: Female | F11: New York | G11: Rochester | H11: PhD | I11: 34332 | J11: 43122 | K11: N/A | L11: Sales | M11: Sales Manager | N11: 133039 | Q11: 00-48990885 | R11: Michael | S11: Mathews | T11: Female | U11: West Virginia | V11: Huntington | W11: Master | X11: 33839 | Y11: 44785 | Z11: N/A | AA11: IT | AB11: IT Manager | AC11: 128150
B12: 00-30370571 | C12: Rebecca | D12: Estes | E12: Female | F12: Michigan | G12: Grand Rapids | H12: PhD | I12: 27872 | J12: 45108 | K12: N/A | L12: Sales | M12: Sales Manager | N12: 127318 | Q12: 00-49657541 | R12: Dustin | S12: Martin | T12: Female | U12: New York | V12: Buffalo | W12: Master | X12: 26594 | Y12: 43052 | Z12: N/A | AA12: Sales | AB12: Sales Manager | AC12: 125832
B13: 00-34077528 | C13: Gregory | D13: Wood | E13: Female | F13: New York | G13: Rochester | H13: Master | I13: 31675 | J13: 43007 | K13: N/A | L13: Finance | M13: Finance Manager | N13: 132723 | Q13: 00-56069176 | R13: Michelle | S13: Ayers | T13: Female | U13: New York | V13: Rochester | W13: PhD | X13: 26493 | Y13: 43142 | Z13: N/A | AA13: Sales | AB13: Sales Manager | AC13: 135055
B14: 00-36772387 | C14: Michelle | D14: Burton | E14: Male | F14: New York | G14: New York City | H14: PhD | I14: 28741 | J14: 42794 | K14: 43160 | L14: Finance | M14: Finance Manager | N14: 122140 | Q14: 00-57263919 | R14: Tracey | S14: Hopkins | T14: Female | U14: Pennsylvania | V14: Pittsburgh | W14: Master | X14: 32830 | Y14: 45621 | Z14: N/A | AA14: Sales | AB14: Sales Manager | AC14: 120572
B15: 00-42521351 | C15: Theresa | D15: Galloway | E15: Female | F15: New York | G15: Rochester | H15: PhD | I15: 21954 | J15: 44087 | K15: N/A | L15: Sales | M15: Sales Manager | N15: 122906 | Q15: 00-62430296 | R15: Jeffrey | S15: Vaughan | T15: Female | U15: Illinois | V15: Chicago | W15: PhD | X15: 22846 | Y15: 42728 | Z15: N/A | AA15: Sales | AB15: Sales Manager | AC15: 130513
B16: 00-44042835 | C16: Raymond | D16: Lopez | E16: Female | F16: New York | G16: Buffalo | H16: PhD | I16: 34275 | J16: 43708 | K16: N/A | L16: IT | M16: IT Manager | N16: 133044 | Q16: 00-67841075 | R16: Barbara | S16: Tran | T16: Female | U16: Michigan | V16: Warren | W16: Master | X16: 28159 | Y16: 42840 | Z16: N/A | AA16: Finance | AB16: Finance Manager | AC16: 134173
B17: 00-46072958 | C17: Stephanie | D17: Murray | E17: Male | F17: New York | G17: New York City | H17: PhD | I17: 34600 | J17: 44837 | K17: 45017 | L17: IT | M17: IT Manager | N17: 120635 | Q17: 00-71836850 | R17: Michael | S17: Brown | T17: Female | U17: North Carolina | V17: Charlotte | W17: Master | X17: 26067 | Y17: 45013 | Z17: N/A | AA17: IT | AB17: IT Manager | AC17: 132590
B18: 00-48990885 | C18: Michael | D18: Mathews | E18: Female | F18: West Virginia | G18: Huntington | H18: Master | I18: 33839 | J18: 44785 | K18: N/A | L18: IT | M18: IT Manager | N18: 128150 | Q18: 00-80276331 | R18: Kristina | S18: Gardner | T18: Female | U18: New York | V18: New York City | W18: PhD | X18: 33006 | Y18: 42805 | Z18: N/A | AA18: Finance | AB18: Finance Manager | AC18: 149377
B19: 00-49657541 | C19: Dustin | D19: Martin | E19: Female | F19: New York | G19: Buffalo | H19: Master | I19: 26594 | J19: 43052 | K19: N/A | L19: Sales | M19: Sales Manager | N19: 125832 | Q19: 00-84386123 | R19: Margaret | S19: Gill | T19: Female | U19: Pennsylvania | V19: Philadelphia | W19: Master | X19: 35076 | Y19: 42634 | Z19: 44049 | AA19: Sales | AB19: Sales Manager | AC19: 124824
B20: 00-56069176 | C20: Michelle | D20: Ayers | E20: Female | F20: New York | G20: Rochester | H20: PhD | I20: 26493 | J20: 43142 | K20: N/A | L20: Sales | M20: Sales Manager | N20: 135055 | Q20: 00-94437310 | R20: Andrew | S20: Garcia | T20: Female | U20: New York | V20: Buffalo | W20: PhD | X20: 22547 | Y20: 45509 | Z20: N/A | AA20: IT | AB20: IT Manager | AC20: 121860
B21: 00-57263919 | C21: Tracey | D21: Hopkins | E21: Female | F21: Pennsylvania | G21: Pittsburgh | H21: Master | I21: 32830 | J21: 45621 | K21: N/A | L21: Sales | M21: Sales Manager | N21: 120572
B22: 00-62430296 | C22: Jeffrey | D22: Vaughan | E22: Female | F22: Illinois | G22: Chicago | H22: PhD | I22: 22846 | J22: 42728 | K22: N/A | L22: Sales | M22: Sales Manager | N22: 130513
B23: 00-67841075 | C23: Barbara | D23: Tran | E23: Female | F23: Michigan | G23: Warren | H23: Master | I23: 28159 | J23: 42840 | K23: N/A | L23: Finance | M23: Finance Manager | N23: 134173
B24: 00-70313693 | C24: Luis | D24: Rogers | E24: Male | F24: New York | G24: New York City | H24: PhD | I24: 25519 | J24: 43801 | K24: N/A | L24: IT | M24: IT Manager | N24: 128906
B25: 00-71836850 | C25: Michael | D25: Brown | E25: Female | F25: North Carolina | G25: Charlotte | H25: Master | I25: 26067 | J25: 45013 | K25: N/A | L25: IT | M25: IT Manager | N25: 132590
B26: 00-80276331 | C26: Kristina | D26: Gardner | E26: Female | F26: New York | G26: New York City | H26: PhD | I26: 33006 | J26: 42805 | K26: N/A | L26: Finance | M26: Finance Manager | N26: 149377
B27: 00-84386123 | C27: Margaret | D27: Gill | E27: Female | F27: Pennsylvania | G27: Philadelphia | H27: Master | I27: 35076 | J27: 42634 | K27: 44049 | L27: Sales | M27: Sales Manager | N27: 124824
B28: 00-94437310 | C28: Andrew | D28: Garcia | E28: Female | F28: New York | G28: Buffalo | H28: PhD | I28: 22547 | J28: 45509 | K28: N/A | L28: IT | M28: IT Manager | N28: 121860
B29: 00-99031467 | C29: Lisa | D29: Rodriguez | E29: Male | F29: New York | G29: Rochester | H29: PhD | I29: 22995 | J29: 45462 | K29: N/A | L29: IT | M29: IT Manager | N29: 131830

Sheet MIN,MAX SALARY
C2: ALL EMPLYS | D2: Male | E2: Female
A3: LOWEST SALARY | C3: =MIN(STAFF!M:M) -> 51835 | D3: =_xlfn.MINIFS(STAFF!M2:M19000,STAFF!D2:D19000,"Male") -> 52612 | E3: =_xlfn.MINIFS(STAFF!M2:M19000,STAFF!D2:D19000,"Female") -> 51835
A4: HIGHEST SALARY | C4: =MAX(STAFF!M:M) -> 149377 | D4: =_xlfn.MAXIFS(STAFF!M2:M19000,STAFF!D2:D19000,"Male") -> 131830 | E4: =_xlfn.MAXIFS(STAFF!M2:M19000,STAFF!D2:D19000,"Female") -> 149377
A5: TOP 5 SLARIES | C5: =LARGE(STAFF!M:M,I5) -> 149377 | D5: {=LARGE(IF(STAFF!D2:D19000="Male",STAFF!M2:M19000),1)} -> 131830 | E5: {=LARGE(IF(STAFF!D2:D19000="Female",STAFF!M2:M19000),J5)} -> 149377 | I5: 1 | J5: 1 | K5: 1
C6: =LARGE(STAFF!M:M,I6) -> 141543 | D6: {=LARGE(IF(STAFF!D3:D19001="Male",STAFF!M3:M19001),1)} -> 131830 | E6: {=LARGE(IF(STAFF!D3:D19001="Female",STAFF!M3:M19001),J6)} -> 141543 | I6: 2 | J6: 2 | K6: 2
C7: =LARGE(STAFF!M:M,I7) -> 135055 | D7: {=LARGE(IF(STAFF!D4:D19002="Male",STAFF!M4:M19002),1)} -> 131830 | E7: {=LARGE(IF(STAFF!D4:D19002="Female",STAFF!M4:M19002),J7)} -> 135055 | I7: 3 | J7: 3 | K7: 3
C8: =LARGE(STAFF!M:M,I8) -> 134173 | D8: {=LARGE(IF(STAFF!D5:D19003="Male",STAFF!M5:M19003),1)} -> 131830 | E8: {=LARGE(IF(STAFF!D5:D19003="Female",STAFF!M5:M19003),J8)} -> 134173 | I8: 4 | J8: 4 | K8: 4
C9: =LARGE(STAFF!M:M,I9) -> 133425 | D9: {=LARGE(IF(STAFF!D6:D19004="Male",STAFF!M6:M19004),1)} -> 131830 | E9: {=LARGE(IF(STAFF!D6:D19004="Female",STAFF!M6:M19004),J9)} -> 133425 | I9: 5 | J9: 5 | K9: 5
A12: TOP 5 SALARIES | C12: =IFERROR(SMALL(STAFF!M:M,I5),0) -> 51835 | D12: {=IFERROR(SMALL(IF(STAFF!D:D="Male",STAFF!M:M),J5),0)} -> 52612 | E12: {=IFERROR(SMALL(IF(STAFF!D:D="Female",STAFF!M:M),K5),0)} -> 51835
A13: FROM LOWEST | C13: =IFERROR(SMALL(STAFF!M:M,I6),0) -> 51865 | D13: {=IFERROR(SMALL(IF(STAFF!D:D="Male",STAFF!M:M),J6),0)} -> 52642 | E13: {=IFERROR(SMALL(IF(STAFF!D:D="Female",STAFF!M:M),K6),0)} -> 51865
C14: =IFERROR(SMALL(STAFF!M:M,I7),0) -> 51887 | D14: {=IFERROR(SMALL(IF(STAFF!D:D="Male",STAFF!M:M),J7),0)} -> 52759 | E14: {=IFERROR(SMALL(IF(STAFF!D:D="Female",STAFF!M:M),K7),0)} -> 51887
C15: =IFERROR(SMALL(STAFF!M:M,I8),0) -> 51887 | D15: {=IFERROR(SMALL(IF(STAFF!D:D="Male",STAFF!M:M),J8),0)} -> 52836 | E15: {=IFERROR(SMALL(IF(STAFF!D:D="Female",STAFF!M:M),K8),0)} -> 51887
C16: =IFERROR(SMALL(STAFF!M:M,I9),0) -> 51919 | D16: {=IFERROR(SMALL(IF(STAFF!D:D="Male",STAFF!M:M),J9),0)} -> 52966 | E16: {=IFERROR(SMALL(IF(STAFF!D:D="Female",STAFF!M:M),K9),0)} -> 51919

Sheet COUNTA FOR DEPT
A1: List of all departments
A3: {=_xlfn.UNIQUE(STAFF!K2:K19000)} -> Customer Service | D3: COUNT | E3: =COUNTA(_xlfn.UNIQUE(STAFF!K2:K19000)) -> 8
A4: Operations
A5: Finance
A6: Sales
A7: Marketing
A8: HR
A9: IT
A10: 0

Sheet VLOOKUP,XLOOKUP
B2: Employee ID | C2: 00-10001272 | F2: With XLOOKUP
B5: First Name | C5: =VLOOKUP(C2,STAFF!A:M,2,FALSE) -> Samuel | F5: =_xlfn.XLOOKUP(C2,STAFF!A:A,STAFF!B:B,"Not Found") -> Samuel
B6: Last Name | C6: =VLOOKUP(C2,STAFF!A:M,3,FALSE) -> Burgess | F6: =_xlfn.XLOOKUP(C2,STAFF!A:A,STAFF!C:C) -> Burgess
B7: Department | C7: =VLOOKUP(C2,STAFF!A:M,11,FALSE) -> Customer Service | F7: =_xlfn.XLOOKUP(C2,STAFF!A:A,STAFF!K:K) -> Customer Service
B8: Salary | C8: =VLOOKUP(C2,STAFF!A:M,13,FALSE) -> 66787 | F8: =_xlfn.XLOOKUP(C2,STAFF!A:A,STAFF!M:M) -> 66787
I11: ENTIRE DATA
B13: LAST | C13: Perry | I13: {=_xlfn.XLOOKUP(C13,STAFF!C:C,STAFF!A:M,"NOT FOUND")} -> 00-10333912 | J13: Angela | K13: Perry | L13: Male | M13: Illinois | N13: Naperville | O13: Bachelor | P13: 26067 | Q13: 43437 | R13: N/A | S13: Operations | T13: Logistics Coordinator | U13: 62346
C14: =MATCH(C13,STAFF!C:C,0) -> 38
I15: {=TRANSPOSE(_xlfn.XLOOKUP(C13,STAFF!C:C,STAFF!A:M))} -> 00-10333912
I16: Angela
B17: Employee ID | C17: =INDEX(STAFF!A:A,MATCH(C13,STAFF!C:C,0)) -> 00-10333912 | F17: =_xlfn.XLOOKUP(C13,STAFF!C:C,STAFF!A:A,"NOT FOUND") -> 00-10333912 | I17: Perry
B18: Department | C18: =INDEX(STAFF!K:K,MATCH(C13,STAFF!C:C,0)) -> Operations | F18: =_xlfn.XLOOKUP(C13,STAFF!C:C,STAFF!K:K,"NOT FOUND") -> Operations | I18: Male
B19: Salary | C19: =INDEX(STAFF!M:M,MATCH(C13,STAFF!C:C,0)) -> 62346 | F19: =_xlfn.XLOOKUP(C13,STAFF!C:C,STAFF!M:M,"NOT FOUND") -> 62346 | I19: Illinois
I20: Naperville
I21: Bachelor
I22: 26067
I23: 43437
I24: N/A
I25: Operations
I26: Logistics Coordinator
I27: 62346

Sheet XLOOKUPWITH MAX
C2: One person | E2: {=_xlfn.XLOOKUP(MAX(STAFF!M:M),STAFF!M:M,STAFF!B:B & " "& STAFF!C:C)} -> Kristina Gardner
C6: All persons | E6: {=_xlfn._xlws.FILTER(STAFF!B:B,STAFF!M:M=MAX(STAFF!M:M))} -> Kristina

Sheet FILTER FOR MONTH MARCH
A1: Employee_ID | B1: First Name | C1: Last Name | D1: Gender | E1: State | F1: City | G1: Education Level | H1: Birthdate | I1: Hiredate | J1: Termdate | K1: Department | L1: Job Title | M1: Salary | N1: Atrrition status | O1: Performance Rating
A2: {=_xlfn._xlws.FILTER(STAFF!A2:O19000,MONTH(STAFF!I2:I19000)=3)} -> 00-10076959 | B2: Mark | C2: Stewart | D2: Male | E2: New York | F2: Buffalo | G2: Bachelor | H2: 23131 | I2: 42825 | J2: N/A | K2: Marketing | L2: Marketing Coordinator | M2: 76850 | N2: Terminated | O2: Satisfactory
A3: 00-10113880 | B3: Brad | C3: Hobbs | D3: Male | E3: New York | F3: Buffalo | G3: High School | H3: 31651 | I3: 42815 | J3: N/A | K3: Marketing | L3: Content Creator | M3: 54733 | N3: Terminated | O3: Good
A4: 00-10147197 | B4: Henry | C4: Mccarthy | D4: Female | E4: New York | F4: Buffalo | G4: Bachelor | H4: 30757 | I4: 44995 | J4: N/A | K4: Operations | L4: Operations Analyst | M4: 56478 | N4: Terminated | O4: Good
A5: 00-10195370 | B5: Daniel | C5: Maxwell | D5: Male | E5: Illinois | F5: Naperville | G5: High School | H5: 25817 | I5: 43180 | J5: N/A | K5: Customer Service | L5: Support Specialist | M5: 64056 | N5: Terminated | O5: Good
A6: 00-10302186 | B6: Amy | C6: Davis | D6: Female | E6: New York | F6: Buffalo | G6: High School | H6: 26766 | I6: 43181 | J6: N/A | K6: Operations | L6: Inventory Specialist | M6: 65488 | N6: Terminated | O6: Satisfactory
A7: 00-10392185 | B7: Sherry | C7: Carpenter | D7: Male | E7: North Carolina | F7: Raleigh | G7: High School | H7: 28486 | I7: 42438 | J7: N/A | K7: Customer Service | L7: Customer Service Representative | M7: 59847 | N7: Terminated | O7: Needs Improvement
A8: 00-10404729 | B8: John | C8: Grimes | D8: Female | E8: Virginia | F8: Virginia Beach | G8: Bachelor | H8: 29781 | I8: 44624 | J8: 44804 | K8: Customer Service | L8: Help Desk Technician | M8: 58407 | N8: Terminated | O8: Good
A9: 00-10470877 | B9: Paul | C9: Day | D9: Male | E9: New York | F9: Rochester | G9: Master | H9: 22624 | I9: 43178 | J9: N/A | K9: HR | L9: HR Coordinator | M9: 54969 | N9: Terminated | O9: Good
A10: 00-10617870 | B10: Erin | C10: Ramos | D10: Female | E10: New York | F10: Buffalo | G10: Bachelor | H10: 31413 | I10: 45370 | J10: N/A | K10: Operations | L10: Operations Manager | M10: 95684 | N10: Terminated | O10: Good
A11: 00-10667294 | B11: David | C11: Sims | D11: Male | E11: New York | F11: New York City | G11: Bachelor | H11: 26498 | I11: 42816 | J11: N/A | K11: Operations | L11: Logistics Coordinator | M11: 66996 | N11: Terminated | O11: Satisfactory
A12: 00-10753570 | B12: Carolyn | C12: Robinson | D12: Female | E12: New York | F12: New York City | G12: Bachelor | H12: 29386 | I12: 43912 | J12: N/A | K12: Customer Service | L12: Support Specialist | M12: 63693 | N12: Terminated | O12: Satisfactory
A13: 00-10959975 | B13: Lori | C13: Daniels | D13: Female | E13: Pennsylvania | F13: Philadelphia | G13: Bachelor | H13: 37328 | I13: 43170 | J13: N/A | K13: Sales | L13: Sales Representative | M13: 58267 | N13: Terminated | O13: Excellent
A14: 00-11031743 | B14: Robert | C14: Newton | D14: Male | E14: New York | F14: New York City | G14: Bachelor | H14: 32868 | I14: 42796 | J14: N/A | K14: Operations | L14: Logistics Coordinator | M14: 64797 | N14: Terminated | O14: Needs Improvement
A15: 00-11190605 | B15: Stephanie | C15: Gibbs | D15: Female | E15: New York | F15: Rochester | G15: Bachelor | H15: 37522 | I15: 43530 | J15: N/A | K15: HR | L15: Recruiter | M15: 69690 | N15: Terminated | O15: Good
A16: 00-11224073 | B16: Albert | C16: Palmer | D16: Male | E16: New York | F16: Buffalo | G16: High School | H16: 32050 | I16: 45352 | J16: N/A | K16: HR | L16: Recruiter | M16: 62801 | N16: Terminated | O16: Excellent
A17: 00-11292919 | B17: Karen | C17: Lamb | D17: Male | E17: Ohio | F17: Cincinnati | G17: Bachelor | H17: 32189 | I17: 43175 | J17: N/A | K17: Customer Service | L17: Support Specialist | M17: 70150 | N17: Terminated | O17: Good
A18: 00-11294689 | B18: Nicole | C18: Manning | D18: Male | E18: New York | F18: Rochester | G18: High School | H18: 23580 | I18: 42824 | J18: N/A | K18: IT | L18: IT Support Specialist | M18: 57322 | N18: Terminated | O18: Good
A19: 00-11306363 | B19: Matthew | C19: Castillo | D19: Female | E19: New York | F19: New York City | G19: Master | H19: 30028 | I19: 43903 | J19: N/A | K19: IT | L19: Software Developer | M19: 107398 | N19: Terminated | O19: Good
A20: 00-11458621 | B20: Donna | C20: Gomez | D20: Male | E20: Michigan | F20: Detroit | G20: Bachelor | H20: 26336 | I20: 43553 | J20: N/A | K20: Operations | L20: Operations Manager | M20: 105680 | N20: Terminated | O20: Satisfactory
... A24: 00-11967696 | B24: Craig | C24: Roth | D24: Male | E24: Illinois | F24: Chicago | G24: Master | H24: 35442 | I24: 42439 | J24: N/A | K24: IT | L24: System Administrator | M24: 72088 | N24: Terminated | O24: Good
A25: 00-12058055 | B25: Bryan | C25: Taylor | D25: Female | E25: New York | F25: New York City | G25: Bachelor | H25: 27556 | I25: 42816 | J25: 43578 | K25: Operations | L25: Logistics Coordinator | M25: 55963 | N25: Terminated | O25: Needs Improvement
A26: 00-12247218 | B26: Adam | C26: Caldwell | D26: Male | E26: North Carolina | F26: Charlotte | G26: Master | H26: 28696 | I26: 42824 | J26: N/A | K26: Sales | L26: Sales Consultant | M26: 77326 | N26: Terminated | O26: Good
A27: 00-12328554 | B27: Erin | C27: Jones | D27: Female | E27: New York | F27: New York City | G27: Master | H27: 33082 | I27: 43190 | J27: N/A | K27: IT | L27: Software Developer | M27: 97588 | N27: Terminated | O27: Satisfactory
A28: 00-12354860 | B28: Katherine | C28: Fowler | D28: Male | E28: New York | F28: New York City | G28: High School | H28: 29965 | I28: 45008 | J28: N/A | K28: Customer Service | L28: Support Specialist | M28: 59438 | N28: Terminated | O28: Satisfactory
A29: 00-12371679 | B29: Cassandra | C29: Simmons | D29: Female | E29: New York | F29: Rochester | G29: Bachelor | H29: 33011 | I29: 45361 | J29: N/A | K29: Sales | L29: Sales Representative | M29: 66440 | N29: Terminated | O29: Excellent
A30: 00-12425579 | B30: George | C30: Sharp | D30: Female | E30: New York | F30: Buffalo | G30: High School | H30: 27389 | I30: 42088 | J30: N/A | K30: Customer Service | L30: Customer Service Representative | M30: 62804 | N30: Terminated | O30: Needs Improvement
A31: 00-12621771 | B31: Timothy | C31: Carpenter | D31: Female | E31: New York | F31: Buffalo | G31: Bachelor | H31: 31811 | I31: 45003 | J31: N/A | K31: Operations | L31: Operations Analyst | M31: 68687 | N31: Terminated | O31: Good
A32: 00-12632034 | B32: Mckenzie | C32: Smith | D32: Female | E32: Pennsylvania | F32: Allentown | G32: PhD | H32: 29644 | I32: 44636 | J32: N/A | K32: Sales | L32: Sales Consultant | M32: 82614 | N32: Terminated | O32: Good
A33: 00-12655477 | B33: Ashley | C33: Alexander | D33: Male | E33: New York | F33: Buffalo | G33: High School | H33: 30562 | I33: 43528 | J33: N/A | K33: Customer Service | L33: Support Specialist | M33: 68154 | N33: Terminated | O33: Good
A34: 00-12795332 | B34: Brian | C34: Grimes | D34: Female | E34: New York | F34: Buffalo | G34: Bachelor | H34: 31219 | I34: 42805 | J34: N/A | K34: Operations | L34: Logistics Coordinator | M34: 62116 | N34: Terminated | O34: Good
A35: 00-12857448 | B35: John | C35: Jacobson | D35: Male | E35: New York | F35: Buffalo | G35: High School | H35: 29130 | I35: 43901 | J35: N/A | K35: Operations | L35: Inventory Specialist | M35: 58008 | N35: Terminated | O35: Needs Improvement
A36: 00-12947014 | B36: David | C36: Frederick | D36: Female | E36: New York | F36: Rochester | G36: Master | H36: 35459 | I36: 43529 | J36: N/A | K36: Operations | L36: Operations Analyst | M36: 81438 | N36: Terminated | O36: Excellent
A37: 00-13235892 | B37: Richard | C37: Montgomery | D37: Male | E37: New York | F37: Rochester | G37: Bachelor | H37: 36834 | I37: 42802 | J37: N/A | K37: Customer Service | L37: Support Specialist | M37: 70659 | N37: Terminated | O37: Excellent
... A45: 00-14255661 | B45: James | C45: Hawkins | D45: Female | E45: New York | F45: Rochester | G45: Bachelor | H45: 36481 | I45: 42457 | J45: N/A | K45: Operations | L45: Logistics Coordinator | M45: 58009 | N45: Terminated | O45: Good
A46: 00-14416002 | B46: Stephen | C46: Scott | D46: Male | E46: Pennsylvania | F46: Pittsburgh | G46: Master | H46: 30628 | I46: 42808 | J46: 45225 | K46: Sales | L46: Sales Specialist | M46: 55995 | N46: Terminated | O46: Excellent
A47: 00-14535123 | B47: Katelyn | C47: Turner | D47: Female | E47: New York | F47: New York City | G47: Master | H47: 29451 | I47: 43912 | J47: N/A | K47: Sales | L47: Sales Consultant | M47: 103135 | N47: Terminated | O47: Good
A48: 00-14548283 | B48: Diana | C48: Simpson | D48: Female | E48: New York | F48: Rochester | G48: Bachelor | H48: 32129 | I48: 44634 | J48: N/A | K48: Operations | L48: Inventory Specialist | M48: 56474 | N48: Terminated | O48: Satisfactory
A49: 00-14840043 | B49: Brian | C49: Schneider | D49: Female | E49: New York | F49: New York City | G49: Bachelor | H49: 33709 | I49: 43161 | J49: N/A | K49: Customer Service | L49: Support Specialist | M49: 56253 | N49: Terminated | O49: Satisfactory
A50: 00-15307982 | B50: Robert | C50: Gutierrez | D50: Male | E50: New York | F50: New York City | G50: High School | H50: 33245 | I50: 42815 | J50: 43456 | K50: Operations | L50: Inventory Specialist | M50: 59202 | N50: Terminated | O50: Needs Improvement
A51: 00-15347831 | B51: Louis | C51: Flores | D51: Female | E51: Ohio | F51: Columbus | G51: Bachelor | H51: 32602 | I51: 42446 | J51: N/A | K51: Operations | L51: Logistics Coordinator | M51: 53665 | N51: Terminated | O51: Satisfactory
A52: 00-15382566 | B52: Kimberly | C52: Wood | D52: Female | E52: New York | F52: Rochester | G52: High School | H52: 31506 | I52: 45013 | J52: N/A | K52: Operations | L52: Inventory Specialist | M52: 60511 | N52: Terminated | O52: Excellent
A53: 00-15450389 | B53: Deanna | C53: Brown | D53: Female | E53: West Virginia | F53: Charleston | G53: Bachelor | H53: 37607 | I53: 42454 | J53: N/A | K53: Customer Service | L53: Help Desk Technician | M53: 71065 | N53: Terminated | O53: Good
A54: 00-15509949 | B54: Dennis | C54: Allen | D54: Male | E54: New York | F54: Buffalo | G54: High School | H54: 30853 | I54: 44625 | J54: N/A | K54: IT | L54: IT Support Specialist | M54: 60892 | N54: Terminated | O54: Good
A55: 00-15519702 | B55: Jason | C55: Williams | D55: Male | E55: New York | F55: Buffalo | G55: Bachelor | H55: 35097 | I55: 43898 | J55: N/A | K55: Customer Service | L55: Customer Service Representative | M55: 70681 | N55: Terminated | O55: Good
A56: 00-15562968 | B56: Dakota | C56: Watson | D56: Female | E56: New York | F56: New York City | G56: Bachelor | H56: 34232 | I56: 43541 | J56: N/A | K56: Finance | L56: Accounts Payable Specialist | M56: 54373 | N56: Terminated | O56: Needs Improvement
A57: 00-15754576 | B57: Jeremiah | C57: Schneider | D57: Male | E57: New York | F57: New York City | G57: Bachelor | H57: 29387 | I57: 42796 | J57: N/A | K57: IT | L57: IT Support Specialist | M57: 70287 | N57: Terminated | O57: Good
A58: 00-15809144 | B58: Michael | C58: Murray | D58: Male | E58: New York | F58: Rochester | G58: High School | H58: 31232 | I58: 42436 | J58: N/A | K58: IT | L58: IT Support Specialist | M58: 56502 | N58: Terminated | O58: Satisfactory
A59: 00-15854522 | B59: Alexander | C59: Rodriguez | D59: Female | E59: North Carolina | F59: Raleigh | G59: Master | H59: 24555 | I59: 44642 | J59: N/A | K59: Finance | L59: Financial Analyst | M59: 84182 | N59: Terminated | O59: Good
A60: 00-16227011 | B60: Heather | C60: Lester | D60: Male | E60: New York | F60: New York City | G60: High School | H60: 36257 | I60: 43190 | J60: N/A | K60: Marketing | L60: Content Creator | M60: 54277 | N60: Terminated | O60: Good
A61: 00-16412872 | B61: Donald | C61: Sanford | D61: Male | E61: New York | F61: Rochester | G61: Bachelor | H61: 25549 | I61: 45371 | J61: N/A | K61: Operations | L61: Inventory Specialist | M61: 70780 | N61: Terminated | O61: Good
A62: 00-16436549 | B62: Brian | C62: Washington | D62: Female | E62: New York | F62: Buffalo | G62: Bachelor | H62: 32272 | I62: 43916 | J62: N/A | K62: Operations | L62: Logistics Coordinator | M62: 59580 | N62: Terminated | O62: Needs Improvement
... A68: 00-16903019 | B68: Connie | C68: Munoz | D68: Female | E68: New York | F68: New York City | G68: Bachelor | H68: 31746 | I68: 44277 | J68: N/A | K68: Operations | L68: Logistics Coordinator | M68: 62970 | N68: Terminated | O68: Good
A69: 00-17538738 | B69: Amanda | C69: Carlson | D69: Female | E69: New York | F69: New York City | G69: Master | H69: 35522 | I69: 42801 | J69: 42991 | K69: Sales | L69: Sales Consultant | M69: 76899 | N69: Terminated | O69: Excellent
A70: 00-17634560 | B70: Mindy | C70: Kane | D70: Female | E70: New York | F70: New York City | G70: High School | H70: 33363 | I70: 45380 | J70: N/A | K70: Customer Service | L70: Customer Service Representative | M70: 53662 | N70: Terminated | O70: Satisfactory
A71: 00-17947134 | B71: Blake | C71: Watts | D71: Male | E71: Michigan | F71: Grand Rapids | G71: High School | H71: 35686 | I71: 43533 | J71: N/A | K71: Marketing | L71: SEO Specialist | M71: 71816 | N71: Terminated | O71: Good
A72: 00-18024377 | B72: Erin | C72: Roberts | D72: Male | E72: New York | F72: Rochester | G72: Bachelor | H72: 21769 | I72: 42824 | J72: N/A | K72: Operations | L72: Logistics Coordinator | M72: 65590 | N72: Terminated | O72: Satisfactory
A73: 00-18036166 | B73: Frank | C73: Key | D73: Male | E73: Virginia | F73: Norfolk | G73: High School | H73: 28121 | I73: 42814 | J73: N/A | K73: Customer Service | L73: Support Specialist | M73: 67409 | N73: Terminated | O73: Good
A74: 00-18036942 | B74: Joshua | C74: Cardenas | D74: Female | E74: New York | F74: Buffalo | G74: High School | H74: 32710 | I74: 42083 | J74: N/A | K74: Customer Service | L74: Customer Service Representative | M74: 60789 | N74: Terminated | O74: Needs Improvement
A75: 00-18169239 | B75: Sylvia | C75: Brooks | D75: Male | E75: New York | F75: Rochester | G75: Bachelor | H75: 36692 | I75: 42823 | J75: N/A | K75: HR | L75: HR Assistant | M75: 62552 | N75: Terminated | O75: Good
A76: 00-18184472 | B76: Ariana | C76: Flynn | D76: Male | E76: New York | F76: New York City | G76: Bachelor | H76: 30438 | I76: 42455 | J76: 43103 | K76: Sales | L76: Sales Representative | M76: 68840 | N76: Terminated | O76: Good
A77: 00-18496074 | B77: Michelle | C77: Gonzales | D77: Female | E77: Illinois | F77: Aurora | G77: Bachelor | H77: 27570 | I77: 43903 | J77: N/A | K77: Customer Service | L77: Help Desk Technician | M77: 69044 | N77: Terminated | O77: Satisfactory
A78: 00-18497890 | B78: Brandon | C78: Allen | D78: Male | E78: New York | F78: New York City | G78: Master | H78: 26026 | I78: 43901 | J78: N/A | K78: Operations | L78: Operations Analyst | M78: 87008 | N78: Terminated | O78: Excellent
A79: 00-18522597 | B79: Michelle | C79: Wilson | D79: Male | E79: Ohio | F79: Cincinnati | G79: Bachelor | H79: 34547 | I79: 44644 | J79: N/A | K79: Sales | L79: Sales Specialist | M79: 85731 | N79: Terminated | O79: Satisfactory
A80: 00-18915990 | B80: Martha | C80: Floyd | D80: Female | E80: New York | F80: New York City | G80: Bachelor | H80: 29693 | I80: 43555 | J80: N/A | K80: Operations | L80: Logistics Coordinator | M80: 60707 | N80: Terminated | O80: Good
A81: 00-19168351 | B81: Curtis | C81: Hernandez | D81: Male | E81: Pennsylvania | F81: Pittsburgh | G81: Bachelor | H81: 32606 | I81: 42824 | J81: N/A | K81: IT | L81: IT Support Specialist | M81: 70217 | N81: Terminated | O81: Good
A82: 00-19281333 | B82: Elizabeth | C82: Shea | D82: Male | E82: New York | F82: Buffalo | G82: Master | H82: 29151 | I82: 44640 | J82: N/A | K82: IT | L82: System Administrator | M82: 92872 | N82: Terminated | O82: Good
A83: 00-19326928 | B83: Edward | C83: Rubio | D83: Female | E83: New York | F83: Buffalo | G83: High School | H83: 30838 | I83: 45358 | J83: N/A | K83: Customer Service | L83: Help Desk Technician | M83: 84468 | N83: Terminated | O83: Needs Improvement
A84: 00-19686066 | B84: Tina | C84: Garcia | D84: Male | E84: New York | F84: Rochester | G84: Master | H84: 28731 | I84: 43171 | J84: N/A | K84: IT | L84: Software Developer | M84: 99394 | N84: Terminated | O84: Good
A85: 00-20117988 | B85: John | C85: Caldwell | D85: Female | E85: New York | F85: New York City | G85: Bachelor | H85: 30243 | I85: 43549 | J85: 43729 | K85: Operations | L85: Operations Analyst | M85: 64183 | N85: Terminated | O85: Needs Improvement
A86: 00-20197356 | B86: Michael | C86: Burns | D86: Female | E86: Michigan | F86: Warren | G86: Bachelor | H86: 31393 | I86: 45376 | J86: N/A | K86: Sales | L86: Sales Consultant | M86: 65951 | N86: Terminated | O86: Good
A87: 00-20204755 | B87: Brenda | C87: Vargas | D87: Male | E87: New York | F87: Rochester | G87: Bachelor | H87: 26874 | I87: 43165 | J87: N/A | K87: Sales | L87: Sales Specialist | M87: 76086 | N87: Terminated | O87: Excellent
A88: 00-20279520 | B88: Kristy | C88: Johnson | D88: Female | E88: New York | F88: New York City | G88: Bachelor | H88: 32051 | I88: 45369 | J88: N/A | K88: Customer Service | L88: Support Specialist | M88: 55611 | N88: Terminated | O88: Excellent
A89: 00-20463550 | B89: Devin | C89: Rice | D89: Male | E89: New York | F89: New York City | G89: Bachelor | H89: 30422 | I89: 42077 | J89: N/A | K89: Marketing | L89: Marketing Coordinator | M89: 74950 | N89: Terminated | O89: Satisfactory
A90: 00-20664018 | B90: Cynthia | C90: Trevino | D90: Female | E90: New York | F90: Buffalo | G90: Bachelor | H90: 29075 | I90: 42457 | J90: N/A | K90: Operations | L90: Logistics Coordinator | M90: 57673 | N90: Terminated | O90: Good
A91: 00-20695820 | B91: Stephen | C91: Ochoa | D91: Female | E91: Ohio | F91: Columbus | G91: Master | H91: 30683 | I91: 43169 | J91: N/A | K91: IT | L91: Software Developer | M91: 104825 | N91: Terminated | O91: Excellent
A92: 00-20698169 | B92: Carol | C92: Hughes | D92: Male | E92: Michigan | F92: Detroit | G92: Bachelor | H92: 22851 | I92: 45374 | J92: N/A | K92: Customer Service | L92: Help Desk Technician | M92: 90667 | N92: Terminated | O92: Good
A93: 00-20741296 | B93: Matthew | C93: Chandler | D93: Male | E93: New York | F93: New York City | G93: Bachelor | H93: 30428 | I93: 44277 | J93: N/A | K93: Sales | L93: Sales Representative | M93: 79569 | N93: Terminated | O93: Good
A94: 00-20892520 | B94: Elizabeth | C94: Brown | D94: Male | E94: Illinois | F94: Chicago | G94: Bachelor | H94: 35000 | I94: 42810 | J94: N/A | K94: IT | L94: IT Support Specialist | M94: 63048 | N94: Terminated | O94: Good
A95: 00-20896797 | B95: Steve | C95: Hernandez | D95: Male | E95: Ohio | F95: Columbus | G95: Bachelor | H95: 34272 | I95: 42804 | J95: 44436 | K95: Finance | L95: Accounts Payable Specialist | M95: 61703 | N95: Terminated | O95: Good
A96: 00-21145168 | B96: Ray | C96: Thomas | D96: Female | E96: Virginia | F96: Virginia Beach | G96: High School | H96: 22849 | I96: 44997 | J96: N/A | K96: Customer Service | L96: Customer Service Representative | M96: 56639 | N96: Terminated | O96: Good
A97: 00-21220004 | B97: Mike | C97: Watson | D97: Male | E97: New York | F97: Buffalo | G97: Bachelor | H97: 24176 | I97: 42802 | J97: N/A | K97: IT | L97: Software Developer | M97: 86291 | N97: Terminated | O97: Good
A98: 00-21222980 | B98: Christian | C98: Hill | D98: Female | E98: Pennsylvania | F98: Philadelphia | G98: High School | H98: 28168 | I98: 43919 | J98: N/A | K98: Marketing | L98: SEO Specialist | M98: 73166 | N98: Terminated | O98: Needs Improvement
A99: 00-21283250 | B99: Matthew | C99: Vargas | D99: Male | E99: New York | F99: New York City | G99: Bachelor | H99: 23634 | I99: 43174 | J99: N/A | K99: Customer Service | L99: Customer Service Representative | M99: 62580 | N99: Terminated | O99: Satisfactory
A100: 00-21328270 | B100: Cassandra | C100: Jackson | D100: Male | E100: New York | F100: New York City | G100: Bachelor | H100: 30392 | I100: 43904 | J100: N/A | K100: Operations | L100: Logistics Coordinator | M100: 65514 | N100: Terminated | O100: Good
A101: 00-21345233 | B101: Michelle | C101: Snyder | D101: Female | E101: North Carolina | F101: Greensboro | G101: Bachelor | H101: 36252 | I101: 44646 | J101: N/A | K101: Operations | L101: Logistics Coordinator | M101: 58883 | N101: Terminated | O101: Excellent
A102: 00-21449650 | B102: Autumn | C102: Hill | D102: Female | E102: Michigan | F102: Grand Rapids | G102: Bachelor | H102: 34990 | I102: 43902 | J102: N/A | K102: Operations | L102: Logistics Coordinator | M102: 60417 | N102: Terminated | O102: Good
A103: 00-21509711 | B103: Daniel | C103: Martin | D103: Male | E103: New York | F103: Rochester | G103: High School | H103: 32847 | I103: 43545 | J103: N/A | K103: Customer Service | L103: Help Desk Technician | M103: 62605 | N103: Terminated | O103: Good
A104: 00-21555506 | B104: Adrian | C104: Brooks | D104: Male | E104: Pennsylvania | F104: Philadelphia | G104: Bachelor | H104: 26055 | I104: 43917 | J104: N/A | K104: IT | L104: Software Developer | M104: 104121 | N104: Terminated | O104: Good
A105: 00-21655936 | B105: Kenneth | C105: Thomas | D105: Male | E105: New York | F105: Rochester | G105: Bachelor | H105: 36609 | I105: 45376 | J105: N/A | K105: Operations | L105: Logistics Coordinator | M105: 68748 | N105: Terminated | O105: Satisfactory
A106: 00-21660923 | B106: Janet | C106: Snow | D106: Female | E106: Pennsylvania | F106: Pittsburgh | G106: PhD | H106: 27291 | I106: 43188 | J106: N/A | K106: Sales | L106: Sales Specialist | M106: 95164 | N106: Terminated | O106: Satisfactory
A107: 00-21689007 | B107: Gary | C107: Wilson | D107: Female | E107: New York | F107: Buffalo | G107: Bachelor | H107: 26564 | I107: 43180 | J107: N/A | K107: Sales | L107: Sales Specialist | M107: 78653 | N107: Terminated | O107: Satisfactory
... A113: 00-22690720 | B113: Jessica | C113: Butler | D113: Male | E113: Pennsylvania | F113: Allentown | G113: Master | H113: 29629 | I113: 44990 | J113: N/A | K113: IT | L113: Software Developer | M113: 102281 | N113: Terminated | O113: Good
A114: 00-22762205 | B114: Jerry | C114: Pham | D114: Male | E114: New York | F114: New York City | G114: Bachelor | H114: 33312 | I114: 43186 | J114: 43366 | K114: Operations | L114: Logistics Coordinator | M114: 70063 | N114: Terminated | O114: Good
A115: 00-23041676 | B115: Lauren | C115: Perkins | D115: Male | E115: New York | F115: Buffalo | G115: Master | H115: 22503 | I115: 42803 | J115: N/A | K115: Operations | L115: Operations Analyst | M115: 84085 | N115: Terminated | O115: Good
A116: 00-23115341 | B116: Steven | C116: Garcia | D116: Female | E116: New York | F116: New York City | G116: Bachelor | H116: 26849 | I116: 43533 | J116: N/A | K116: Customer Service | L116: Customer Service Representative | M116: 60869 | N116: Terminated | O116: Good
A117: 00-23253224 | B117: Jamie | C117: Santana | D117: Female | E117: New York | F117: New York City | G117: Bachelor | H117: 35326 | I117: 43172 | J117: N/A | K117: Operations | L117: Inventory Specialist | M117: 54308 | N117: Terminated | O117: Good
A118: 00-23281710 | B118: Tara | C118: Bailey | D118: Female | E118: Illinois | F118: Chicago | G118: Bachelor | H118: 35823 | I118: 43538 | J118: N/A | K118: Customer Service | L118: Customer Service Representative | M118: 59214 | N118: Terminated | O118: Excellent
A119: 00-23416165 | B119: Lauren | C119: Perkins | D119: Female | E119: New York | F119: Rochester | G119: High School | H119: 22024 | I119: 45377 | J119: N/A | K119: Operations | L119: Inventory Specialist | M119: 57338 | N119: Terminated | O119: Good
A120: 00-23419256 | B120: Dorothy | C120: Tucker | D120: Female | E120: New York | F120: New York City | G120: Bachelor | H120: 33102 | I120: 42443 | J120: 42623 | K120: Marketing | L120: SEO Specialist | M120: 81253 | N120: Terminated | O120: Excellent
...

Sheet FILTER FOR WEEKDAYS (MONDAY)
B1: Employee_ID | C1: First Name | D1: Last Name | E1: Gender | F1: State | G1: City | H1: Education Level | I1: Birthdate | J1: Hiredate | K1: Termdate | L1: Department | M1: Job Title | N1: Salary | O1: Atrrition status | P1: Performance Rating | R1: CHECK
B2: {=_xlfn._xlws.FILTER(STAFF!A2:O19000,(STAFF!D2:D19000="Female")*(WEEKDAY(STAFF!I2:I19000,2)=1))} -> 00-10047461 | C2: Steven | D2: Armstrong | E2: Female | F2: Illinois | G2: Naperville | H2: Bachelor | I2: 33952 | J2: 42590 | K2: N/A | L2: Finance | M2: Accountant | N2: 70778 | O2: Terminated | P2: Satisfactory | R2: =WEEKDAY(J3,2)=1 -> TRUE
B3: 00-10080009 | C3: Gabrielle | D3: Crane | E3: Female | F3: New York | G3: Buffalo | H3: Bachelor | I3: 28399 | J3: 44935 | K3: N/A | L3: Sales | M3: Sales Representative | N3: 59328 | O3: Terminated | P3: Good | R3: =WEEKDAY(J4,2)=1 -> TRUE
B4: 00-10122731 | C4: Travis | D4: Aguirre | E4: Female | F4: Ohio | G4: Cleveland | H4: Master | I4: 25354 | J4: 42422 | K4: N/A | L4: Operations | M4: Operations Analyst | N4: 79145 | O4: Terminated | P4: Excellent | R4: =WEEKDAY(J5,2)=1 -> TRUE
B5: 00-10225283 | C5: Ryan | D5: Long | E5: Female | F5: New York | G5: Rochester | H5: High School | I5: 26606 | J5: 43115 | K5: N/A | L5: Operations | M5: Inventory Specialist | N5: 59233 | O5: Terminated | P5: Satisfactory | R5: =WEEKDAY(J6,2)=1 -> TRUE
B6: 00-10256489 | C6: Sue | D6: Howe | E6: Female | F6: New York | G6: Buffalo | H6: Bachelor | I6: 29633 | J6: 45418 | K6: N/A | L6: Sales | M6: Sales Representative | N6: 68287 | O6: Terminated | P6: Satisfactory | R6: =WEEKDAY(J7,2)=1 -> TRUE
B7: 00-10261534 | C7: Kevin | D7: Potter | E7: Female | F7: Ohio | G7: Cincinnati | H7: Bachelor | I7: 28211 | J7: 45467 | K7: N/A | L7: Operations | M7: Logistics Coordinator | N7: 62856 | O7: Terminated | P7: Good | R7: =WEEKDAY(J8,2)=1 -> TRUE
B8: 00-10289289 | C8: Robert | D8: Shields | E8: Female | F8: New York | G8: New York City | H8: Bachelor | I8: 28700 | J8: 45313 | K8: 45493 | L8: Customer Service | M8: Help Desk Technician | N8: 61403 | O8: Terminated | P8: Good | R8: =WEEKDAY(J9,2)=1 -> TRUE
B9: 00-10339260 | C9: Diana | D9: Jones | E9: Female | F9: New York | G9: Rochester | H9: Bachelor | I9: 26885 | J9: 43815 | K9: N/A | L9: Marketing | M9: SEO Specialist | N9: 61326 | O9: Terminated | P9: Good | R9: =WEEKDAY(J10,2)=1 -> TRUE
B10: 00-10446705 | C10: Michelle | D10: Johnson | E10: Female | F10: New York | G10: Buffalo | H10: Bachelor | I10: 37372 | J10: 45446 | K10: N/A | L10: Customer Service | M10: Support Specialist | N10: 54933 | O10: Terminated | P10: Good | R10: =WEEKDAY(J11,2)=1 -> TRUE
B11: 00-10457051 | C11: Christopher | D11: Pitts | E11: Female | F11: New York | G11: Buffalo | H11: Bachelor | I11: 23453 | J11: 42380 | K11: N/A | L11: Sales | M11: Sales Representative | N11: 61979 | O11: Terminated | P11: Good | R11: =WEEKDAY(J12,2)=1 -> TRUE
B12: 00-10466177 | C12: Joseph | D12: Diaz | E12: Female | F12: Michigan | G12: Warren | H12: Bachelor | I12: 33369 | J12: 44718 | K12: 44898 | L12: Finance | M12: Accountant | N12: 53179 | O12: Terminated | P12: Satisfactory | R12: =WEEKDAY(J13,2)=1 -> TRUE
B13: 00-10691813 | C13: Robert | D13: Woodard | E13: Female | F13: New York | G13: Buffalo | H13: High School | I13: 23506 | J13: 43374 | K13: N/A | L13: Customer Service | M13: Support Specialist | N13: 61344 | O13: Terminated | P13: Satisfactory | R13: =WEEKDAY(J14,2)=1 -> TRUE
B14: 00-10865811 | C14: Debbie | D14: Klein | E14: Female | F14: New York | G14: Rochester | H14: Bachelor | I14: 25616 | J14: 45145 | K14: N/A | L14: Marketing | M14: Content Creator | N14: 57329 | O14: Terminated | P14: Satisfactory | R14: =WEEKDAY(J15,2)=1 -> TRUE
B15: 00-10884169 | C15: Elizabeth | D15: Spence | E15: Female | F15: New York | G15: New York City | H15: Bachelor | I15: 24809 | J15: 42793 | K15: N/A | L15: Sales | M15: Sales Representative | N15: 69161 | O15: Terminated | P15: Good | R15: =WEEKDAY(J16,2)=1 -> TRUE
B16: 00-11020743 | C16: Elizabeth | D16: Wright | E16: Female | F16: Michigan | G16: Warren | H16: Bachelor | I16: 36446 | J16: 45558 | K16: N/A | L16: Finance | M16: Accounts Payable Specialist | N16: 59278 | O16: Terminated | P16: Needs Improvement | R16: =WEEKDAY(J17,2)=1 -> TRUE
B17: 00-11116303 | C17: Danny | D17: Reed | E17: Female | F17: New York | G17: New York City | H17: PhD | I17: 29458 | J17: 44655 | K17: N/A | L17: IT | M17: IT Manager | N17: 113352 | O17: Terminated | P17: Excellent | R17: =WEEKDAY(J18,2)=1 -> TRUE
B18: 00-11162685 | C18: Catherine | D18: Baker | E18: Female | F18: Ohio | G18: Columbus | H18: Bachelor | I18: 31897 | J18: 42996 | K18: N/A | L18: Marketing | M18: Marketing Coordinator | N18: 67298 | O18: Terminated | P18: Satisfactory | R18: =WEEKDAY(J19,2)=1 -> TRUE
B19: 00-11385159 | C19: Lori | D19: Davis | E19: Female | F19: New York | G19: Buffalo | H19: Bachelor | I19: 32697 | J19: 43703 | K19: N/A | L19: Customer Service | M19: Help Desk Technician | N19: 69757 | O19: Terminated | P19: Good | R19: =WEEKDAY(J20,2)=1 -> TRUE
B20: 00-11558972 | C20: Anna | D20: Brown | E20: Female | F20: Ohio | G20: Cleveland | H20: PhD | I20: 27116 | J20: 42933 | K20: N/A | L20: Sales | M20: Sales Specialist | N20: 95430 | O20: Terminated | P20: Satisfactory | R20: =WEEKDAY(J21,2)=1 -> TRUE
B21: 00-11760963 | C21: Erica | D21: Rangel | E21: Female | F21: New York | G21: New York City | H21: Bachelor | I21: 29612 | J21: 42779 | K21: N/A | L21: Finance | M21: Financial Analyst | N21: 85672 | O21: Terminated | P21: Good | R21: =WEEKDAY(J22,2)=1 -> TRUE
B22: 00-12193574 | C22: Elizabeth | D22: King | E22: Female | F22: New York | G22: Rochester | H22: Bachelor | I22: 24231 | J22: 43969 | K22: N/A | L22: Finance | M22: Accountant | N22: 87983 | O22: Terminated | P22: Needs Improvement | R22: =WEEKDAY(J23,2)=1 -> TRUE
B23: 00-12423190 | C23: Lisa | D23: Erickson | E23: Female | F23: New York | G23: New York City | H23: Bachelor | I23: 36727 | J23: 44389 | K23: N/A | L23: Finance | M23: Accountant | N23: 75070 | O23: Terminated | P23: Satisfactory | R23: =WEEKDAY(J24,2)=1 -> TRUE
B24: 00-12641440 | C24: Dustin | D24: Nelson | E24: Female | F24: New York | G24: Buffalo | H24: Master | I24: 34240 | J24: 42541 | K24: N/A | L24: Operations | M24: Operations Analyst | N24: 82759 | O24: Terminated | P24: Good | R24: =WEEKDAY(J25,2)=1 -> TRUE
... B49: 00-16986408 | C49: Mary | D49: Mcpherson | E49: Female | F49: New York | G49: New York City | H49: Bachelor | I49: 36711 | J49: 42786 | K49: N/A | L49: Sales | M49: Sales Representative | N49: 63747 | O49: Terminated | P49: Good | R49: =WEEKDAY(J50,2)=1 -> TRUE
B50: 00-17195288 | C50: Curtis | D50: Barton | E50: Female | F50: New York | G50: New York City | H50: High School | I50: 32692 | J50: 43066 | K50: 43453 | L50: Marketing | M50: Content Creator | N50: 53525 | O50: Terminated | P50: Needs Improvement | R50: =WEEKDAY(J51,2)=1 -> TRUE
B51: 00-17200210 | C51: John | D51: Edwards | E51: Female | F51: New York | G51: Rochester | H51: High School | I51: 32899 | J51: 42863 | K51: N/A | L51: IT | M51: IT Support Specialist | N51: 57456 | O51: Terminated | P51: Needs Improvement | R51: =WEEKDAY(J52,2)=1 -> TRUE
B52: 00-17203266 | C52: Christine | D52: Cole | E52: Female | F52: New York | G52: New York City | H52: Bachelor | I52: 25607 | J52: 42674 | K52: N/A | L52: Marketing | M52: Marketing Manager | N52: 89713 | O52: Terminated | P52: Satisfactory | R52: =WEEKDAY(J53,2)=1 -> TRUE
B53: 00-17303355 | C53: Amber | D53: Gonzalez | E53: Female | F53: New York | G53: Buffalo | H53: Bachelor | I53: 30869 | J53: 43213 | K53: N/A | L53: Sales | M53: Sales Specialist | N53: 54735 | O53: Terminated | P53: Satisfactory | R53: =WEEKDAY(J54,2)=1 -> TRUE
B54: 00-17467311 | C54: John | D54: Martinez | E54: Female | F54: Michigan | G54: Detroit | H54: High School | I54: 34712 | J54: 43640 | K54: 44464 | L54: Customer Service | M54: Help Desk Technician | N54: 84792 | O54: Terminated | P54: Excellent | R54: =WEEKDAY(J55,2)=1 -> TRUE
B55: 00-17653101 | C55: Amy | D55: Ortega | E55: Female | F55: New York | G55: Buffalo | H55: High School | I55: 28820 | J55: 45285 | K55: N/A | L55: Customer Service | M55: Help Desk Technician | N55: 78098 | O55: Terminated | P55: Good | R55: =WEEKDAY(J56,2)=1 -> TRUE
B56: 00-18311653 | C56: Timothy | D56: Robertson | E56: Female | F56: Michigan | G56: Grand Rapids | H56: PhD | I56: 22457 | J56: 44459 | K56: N/A | L56: Sales | M56: Sales Specialist | N56: 75297 | O56: Terminated | P56: Excellent | R56: =WEEKDAY(J57,2)=1 -> TRUE
B57: 00-18429833 | C57: Andrew | D57: Nguyen | E57: Female | F57: New York | G57: New York City | H57: High School | I57: 25659 | J57: 42681 | K57: N/A | L57: Customer Service | M57: Customer Service Representative | N57: 57377 | O57: Terminated | P57: Needs Improvement | R57: =WEEKDAY(J58,2)=1 -> TRUE
B58: 00-18545499 | C58: Jose | D58: Turner | E58: Female | F58: New York | G58: Rochester | H58: Bachelor | I58: 33396 | J58: 45047 | K58: N/A | L58: Marketing | M58: Marketing Coordinator | N58: 70710 | O58: Terminated | P58: Satisfactory | R58: =WEEKDAY(J59,2)=1 -> TRUE
B59: 00-18678230 | C59: Patricia | D59: Galvan | E59: Female | F59: Virginia | G59: Norfolk | H59: Bachelor | I59: 22222 | J59: 43661 | K59: N/A | L59: Customer Service | M59: Customer Service Representative | N59: 66151 | O59: Terminated | P59: Good | R59: =WEEKDAY(J60,2)=1 -> TRUE
B60: 00-18852788 | C60: Adam | D60: Webb | E60: Female | F60: New York | G60: Buffalo | H60: Bachelor | I60: 37824 | J60: 43087 | K60: N/A | L60: Finance | M60: Accounts Payable Specialist | N60: 54561 | O60: Terminated | P60: Excellent | R60: =WEEKDAY(J61,2)=1 -> TRUE
B61: 00-18949617 | C61: Andrea | D61: Thompson | E61: Female | F61: Michigan | G61: Detroit | H61: Master | I61: 28784 | J61: 42240 | K61: N/A | L61: Operations | M61: Operations Analyst | N61: 81909 | O61: Terminated | P61: Excellent | R61: =WEEKDAY(J62,2)=1 -> TRUE
B62: 00-19257341 | C62: Brittany | D62: Sanders | E62: Female | F62: Pennsylvania | G62: Allentown | H62: PhD | I62: 34294 | J62: 44193 | K62: N/A | L62: Sales | M62: Sales Specialist | N62: 72753 | O62: Terminated | P62: Satisfactory | R62: =WEEKDAY(J63,2)=1 -> TRUE
B63: 00-19289546 | C63: Colleen | D63: Skinner | E63: Female | F63: New York | G63: New York City | H63: Bachelor | I63: 29921 | J63: 43297 | K63: 43477 | L63: Operations | M63: Inventory Specialist | N63: 63169 | O63: Terminated | P63: Good | R63: =WEEKDAY(J64,2)=1 -> TRUE
B64: 00-19338403 | C64: Judy | D64: Wilson | E64: Female | F64: Pennsylvania | G64: Pittsburgh | H64: Bachelor | I64: 33246 | J64: 44144 | K64: N/A | L64: Operations | M64: Operations Analyst | N64: 75587 | O64: Terminated | P64: Good | R64: =WEEKDAY(J65,2)=1 -> TRUE
B65: 00-19447334 | C65: Kelsey | D65: Quinn | E65: Female | F65: New York | G65: New York City | H65: Bachelor | I65: 35091 | J65: 45040 | K65: N/A | L65: Sales | M65: Sales Representative | N65: 61454 | O65: Terminated | P65: Satisfactory | R65: =WEEKDAY(J66,2)=1 -> TRUE
B66: 00-19484050 | C66: Dennis | D66: Wilson | E66: Female | F66: New York | G66: Buffalo | H66: Bachelor | I66: 29912 | J66: 42359 | K66: N/A | L66: Operations | M66: Operations Analyst | N66: 83794 | O66: Terminated | P66: Satisfactory | R66: =WEEKDAY(J67,2)=1 -> TRUE
B67: 00-19935807 | C67: Sarah | D67: Black | E67: Female | F67: New York | G67: Rochester | H67: Bachelor | I67: 35076 | J67: 43612 | K67: N/A | L67: Sales | M67: Sales Representative | N67: 58828 | O67: Terminated | P67: Good | R67: =WEEKDAY(J68,2)=1 -> TRUE
B68: 00-19954260 | C68: Justin | D68: Goodman | E68: Female | F68: New York | G68: New York City | H68: Bachelor | I68: 30575 | J68: 43640 | K68: 45321 | L68: Customer Service | M68: Customer Service Representative | N68: 61555 | O68: Terminated | P68: Good | R68: =WEEKDAY(J69,2)=1 -> TRUE
B69: 00-20112592 | C69: Alexis | D69: Martinez | E69: Female | F69: New York | G69: Buffalo | H69: Bachelor | I69: 32363 | J69: 43619 | K69: N/A | L69: Marketing | M69: Marketing Manager | N69: 95478 | O69: Terminated | P69: Good | R69: =WEEKDAY(J70,2)=1 -> TRUE
B70: 00-20117988 | C70: John | D70: Caldwell | E70: Female | F70: New York | G70: New York City | H70: Bachelor | I70: 30243 | J70: 43549 | K70: 43729 | L70: Operations | M70: Operations Analyst | N70: 64183 | O70: Terminated | P70: Needs Improvement | R70: =WEEKDAY(J71,2)=1 -> TRUE
B71: 00-20197356 | C71: Michael | D71: Burns | E71: Female | F71: Michigan | G71: Warren | H71: Bachelor | I71: 31393 | J71: 45376 | K71: N/A | L71: Sales | M71: Sales Consultant | N71: 65951 | O71: Terminated | P71: Good | R71: =WEEKDAY(J72,2)=1 -> TRUE
B72: 00-20242515 | C72: James | D72: Graham | E72: Female | F72: Ohio | G72: Cincinnati | H72: Bachelor | I72: 30214 | J72: 42835 | K72: N/A | L72: IT | M72: Software Developer | N72: 92899 | O72: Terminated | P72: Good | R72: =WEEKDAY(J73,2)=1 -> TRUE
B73: 00-20279520 | C73: Kristy | D73: Johnson | E73: Female | F73: New York | G73: New York City | H73: Bachelor | I73: 32051 | J73: 45369 | K73: N/A | L73: Customer Service | M73: Support Specialist | N73: 55611 | O73: Terminated | P73: Excellent | R73: =WEEKDAY(J74,2)=1 -> TRUE
B74: 00-20361818 | C74: Donna | D74: Perry | E74: Female | F74: New York | G74: New York City | H74: High School | I74: 26068 | J74: 44690 | K74: N/A | L74: Marketing | M74: Content Creator | N74: 56385 | O74: Terminated | P74: Needs Improvement | R74: =WEEKDAY(J75,2)=1 -> TRUE
B75: 00-20436008 | C75: Juan | D75: Gregory | E75: Female | F75: New York | G75: Rochester | H75: Bachelor | I75: 32718 | J75: 45285 | K75: N/A | L75: Operations | M75: Operations Analyst | N75: 79281 | O75: Terminated | P75: Good | R75: =WEEKDAY(J76,2)=1 -> TRUE
B76: 00-20526386 | C76: Richard | D76: Davis | E76: Female | F76: New York | G76: New York City | H76: Bachelor | I76: 31153 | J76: 43885 | K76: 44065 | L76: Customer Service | M76: Support Specialist | N76: 56682 | O76: Terminated | P76: Satisfactory | R76: =WEEKDAY(J77,2)=1 -> TRUE
B77: 00-20641856 | C77: Jeffrey | D77: Powell | E77: Female | F77: Pennsylvania | G77: Philadelphia | H77: High School | I77: 31511 | J77: 42961 | K77: N/A | L77: Customer Service | M77: Help Desk Technician | N77: 73594 | O77: Terminated | P77: Good | R77: =WEEKDAY(J78,2)=1 -> TRUE
B78: 00-20664018 | C78: Cynthia | D78: Trevino | E78: Female | F78: New York | G78: Buffalo | H78: Bachelor | I78: 29075 | J78: 42457 | K78: N/A | L78: Operations | M78: Logistics Coordinator | N78: 57673 | O78: Terminated | P78: Good | R78: =WEEKDAY(J79,2)=1 -> TRUE
B79: 00-21123747 | C79: Christine | D79: Gardner | E79: Female | F79: New York | G79: New York City | H79: High School | I79: 33012 | J79: 42415 | K79: N/A | L79: Customer Service | M79: Support Specialist | N79: 53065 | O79: Terminated | P79: Satisfactory | R79: =WEEKDAY(J80,2)=1 -> TRUE
B80: 00-21316066 | C80: Angela | D80: Anderson | E80: Female | F80: New York | G80: New York City | H80: Bachelor | I80: 33632 | J80: 44788 | K80: N/A | L80: Marketing | M80: SEO Specialist | N80: 64768 | O80: Terminated | P80: Excellent | R80: =WEEKDAY(J81,2)=1 -> TRUE
B81: 00-21340498 | C81: Marc | D81: Mitchell | E81: Female | F81: Virginia | G81: Norfolk | H81: Bachelor | I81: 26947 | J81: 42478 | K81: N/A | L81: Customer Service | M81: Support Specialist | N81: 58313 | O81: Terminated | P81: Good | R81: =WEEKDAY(J82,2)=1 -> TRUE
B82: 00-21403835 | C82: David | D82: Andrade | E82: Female | F82: New York | G82: Buffalo | H82: High School | I82: 24864 | J82: 42786 | K82: N/A | L82: Operations | M82: Inventory Specialist | N82: 61916 | O82: Terminated | P82: Needs Improvement | R82: =WEEKDAY(J83,2)=1 -> TRUE
B83: 00-21432787 | C83: Gabrielle | D83: Trujillo | E83: Female | F83: New York | G83: New York City | H83: Bachelor | I83: 25688 | J83: 43409 | K83: 43589 | L83: Customer Service | M83: Support Specialist | N83: 57059 | O83: Terminated | P83: Satisfactory | R83: =WEEKDAY(J84,2)=1 -> TRUE
B84: 00-21589740 | C84: Jean | D84: Luna | E84: Female | F84: New York | G84: Buffalo | H84: High School | I84: 25727 | J84: 44613 | K84: N/A | L84: Customer Service | M84: Support Specialist | N84: 55315 | O84: Terminated | P84: Excellent | R84: =WEEKDAY(J85,2)=1 -> TRUE
B85: 00-21842256 | C85: Jordan | D85: Gonzales | E85: Female | F85: New York | G85: Rochester | H85: Bachelor | I85: 30624 | J85: 43136 | K85: N/A | L85: Operations | M85: Logistics Coordinator | N85: 62489 | O85: Terminated | P85: Good | R85: =WEEKDAY(J86,2)=1 -> TRUE
B86: 00-21902499 | C86: Christopher | D86: Ramsey | E86: Female | F86: New York | G86: Rochester | H86: High School | I86: 26901 | J86: 42842 | K86: N/A | L86: Marketing | M86: Content Creator | N86: 59307 | O86: Terminated | P86: Good | R86: =WEEKDAY(J87,2)=1 -> TRUE
B87: 00-21964334 | C87: Ashley | D87: Simmons | E87: Female | F87: New York | G87: New York City | H87: Bachelor | I87: 33142 | J87: 44683 | K87: N/A | L87: Operations | M87: Logistics Coordinator | N87: 55448 | O87: Terminated | P87: Satisfactory | R87: =WEEKDAY(J88,2)=1 -> TRUE
B88: 00-22225702 | C88: Timothy | D88: Freeman | E88: Female | F88: Michigan | G88: Grand Rapids | H88: Bachelor | I88: 33376 | J88: 45271 | K88: N/A | L88: IT | M88: IT Support Specialist | N88: 60048 | O88: Terminated | P88: Satisfactory | R88: =WEEKDAY(J89,2)=1 -> TRUE
B89: 00-22227594 | C89: Raymond | D89: Lewis | E89: Female | F89: Michigan | G89: Warren | H89: Master | I89: 32248 | J89: 42884 | K89: N/A | L89: IT | M89: System Administrator | N89: 81369 | O89: Terminated | P89: Good | R89: =WEEKDAY(J90,2)=1 -> TRUE
B90: 00-22775337 | C90: John | D90: Davenport | E90: Female | F90: Pennsylvania | G90: Allentown | H90: Bachelor | I90: 29740 | J90: 42156 | K90: 44398 | L90: Operations | M90: Logistics Coordinator | N90: 57215 | O90: Terminated | P90: Good | R90: =WEEKDAY(J91,2)=1 -> TRUE
B91: 00-22965862 | C91: Brenda | D91: Silva | E91: Female | F91: New York | G91: Buffalo | H91: Bachelor | I91: 32156 | J91: 44928 | K91: N/A | L91: Operations | M91: Logistics Coordinator | N91: 57301 | O91: Terminated | P91: Excellent | R91: =WEEKDAY(J92,2)=1 -> TRUE
B92: 00-23082934 | C92: Jacqueline | D92: Pace | E92: Female | F92: Illinois | G92: Chicago | H92: High School | I92: 29286 | J92: 45278 | K92: N/A | L92: Operations | M92: Inventory Specialist | N92: 64134 | O92: Terminated | P92: Needs Improvement | R92: =WEEKDAY(J93,2)=1 -> TRUE
B93: 00-23381785 | C93: Jocelyn | D93: Murphy | E93: Female | F93: New York | G93: Buffalo | H93: Master | I93: 24794 | J93: 44305 | K93: N/A | L93: IT | M93: System Administrator | N93: 79363 | O93: Terminated | P93: Excellent | R93: =WEEKDAY(J94,2)=1 -> TRUE
B94: 00-23419256 | C94: Dorothy | D94: Tucker | E94: Female | F94: New York | G94: New York City | H94: Bachelor | I94: 33102 | J94: 42443 | K94: 42623 | L94: Marketing | M94: SEO Specialist | N94: 81253 | O94: Terminated | P94: Excellent | R94: =WEEKDAY(J95,2)=1 -> TRUE
B95: 00-23430634 | C95: Vincent | D95: Ross | E95: Female | F95: New York | G95: Rochester | H95: PhD | I95: 34332 | J95: 43122 | K95: N/A | L95: Sales | M95: Sales Manager | N95: 133039 | O95: Terminated | P95: Good | R95: =WEEKDAY(J96,2)=1 -> TRUE
B96: 00-23652183 | C96: Brenda | D96: Fuller | E96: Female | F96: Ohio | G96: Columbus | H96: PhD | I96: 23704 | J96: 45187 | K96: N/A | L96: Sales | M96: Sales Consultant | N96: 112552 | O96: Terminated | P96: Good | R96: =WEEKDAY(J97,2)=1 -> TRUE
B97: 00-23669886 | C97: Sandra | D97: Yates | E97: Female | F97: Michigan | G97: Warren | H97: Bachelor | I97: 24803 | J97: 43136 | K97: N/A | L97: Operations | M97: Inventory Specialist | N97: 57437 | O97: Terminated | P97: Excellent | R97: =WEEKDAY(J98,2)=1 -> TRUE
B98: 00-23693384 | C98: Daniel | D98: Carey | E98: Female | F98: New York | G98: New York City | H98: Bachelor | I98: 26025 | J98: 42814 | K98: N/A | L98: Customer Service | M98: Support Specialist | N98: 57802 | O98: Terminated | P98: Satisfactory | R98: =WEEKDAY(J99,2)=1 -> TRUE
B99: 00-23698845 | C99: Jennifer | D99: Fitzgerald | E99: Female | F99: New York | G99: Rochester | H99: Bachelor | I99: 36559 | J99: 42884 | K99: N/A | L99: Sales | M99: Sales Representative | N99: 66440 | O99: Terminated | P99: Good | R99: =WEEKDAY(J100,2)=1 -> TRUE
B100: 00-23948250 | C100: Brandy | D100: Johnson | E100: Female | F100: Michigan | G100: Warren | H100: PhD | I100: 26096 | J100: 42821 | K100: N/A | L100: Sales | M100: Sales Consultant | N100: 96485 | O100: Terminated | P100: Good | R100: =WEEKDAY(J101,2)=1 -> TRUE
B101: 00-24111073 | C101: Jacob | D101: Andersen | E101: Female | F101: New York | G101: New York City | H101: Bachelor | I101: 35381 | J101: 45607 | K101: N/A | L101: Customer Service | M101: Support Specialist | N101: 61604 | O101: Terminated | P101: Good | R101: =WEEKDAY(J102,2)=1 -> TRUE
B102: 00-24161873 | C102: Sean | D102: White | E102: Female | F102: New York | G102: New York City | H102: PhD | I102: 25006 | J102: 44781 | K102: N/A | L102: Sales | M102: Sales Specialist | N102: 79991 | O102: Terminated | P102: Excellent | R102: =WEEKDAY(J103,2)=1 -> TRUE
B103: 00-24857823 | C103: Douglas | D103: Lane | E103: Female | F103: New York | G103: Rochester | H103: High School | I103: 29005 | J103: 45614 | K103: N/A | L103: Customer Service | M103: Support Specialist | N103: 61470 | O103: Terminated | P103: Good | R103: =WEEKDAY(J104,2)=1 -> TRUE
B104: 00-25125464 | C104: Sarah | D104: Hoover | E104: Female | F104: Michigan | G104: Grand Rapids | H104: High School | I104: 28744 | J104: 42226 | K104: N/A | L104: Customer Service | M104: Help Desk Technician | N104: 59599 | O104: Terminated | P104: Satisfactory | R104: =WEEKDAY(J105,2)=1 -> TRUE
B105: 00-25253695 | C105: Theresa | D105: Lane | E105: Female | F105: New York | G105: Rochester | H105: Bachelor | I105: 34883 | J105: 44837 | K105: N/A | L105: Sales | M105: Sales Specialist | N105: 61466 | O105: Terminated | P105: Satisfactory | R105: =WEEKDAY(J106,2)=1 -> TRUE
B106: 00-25284337 | C106: Daniel | D106: Griffin | E106: Female | F106: New York | G106: Buffalo | H106: Bachelor | I106: 33787 | J106: 43787 | K106: N/A | L106: IT | M106: Software Developer | N106: 78653 | O106: Terminated | P106: Good | R106: =WEEKDAY(J107,2)=1 -> TRUE
B107: 00-25419645 | C107: Tammy | D107: Phillips | E107: Female | F107: New York | G107: New York City | H107: High School | I107: 28381 | J107: 44900 | K107: 45080 | L107: Customer Service | M107: Support Specialist | N107: 67032 | O107: Terminated | P107: Needs Improvement | R107: =WEEKDAY(J108,2)=1 -> TRUE
B108: 00-25511151 | C108: Stephen | D108: Roberts | E108: Female | F108: Pennsylvania | G108: Philadelphia | H108: Master | I108: 30974 | J108: 43626 | K108: N/A | L108: Sales | M108: Sales Specialist | N108: 74365 | O108: Terminated | P108: Excellent | R108: =WEEKDAY(J109,2)=1 -> TRUE
B109: 00-25583513 | C109: Zachary | D109: Jones | E109: Female | F109: New York | G109: Rochester | H109: High School | I109: 29639 | J109: 43962 | K109: N/A | L109: Customer Service | M109: Help Desk Technician | N109: 72123 | O109: Terminated | P109: Excellent | R109: =WEEKDAY(J110,2)=1 -> TRUE
B110: 00-26050250 | C110: Donna | D110: Edwards | E110: Female | F110: Michigan | G110: Warren | H110: High School | I110: 23234 | J110: 43325 | K110: N/A | L110: Customer Service | M110: Customer Service Representative | N110: 62574 | O110: Terminated | P110: Satisfactory | R110: =WEEKDAY(J111,2)=1 -> TRUE
B111: 00-26188599 | C111: Stephanie | D111: Stevens | E111: Female | F111: Pennsylvania | G111: Allentown | H111: High School | I111: 35250 | J111: 43913 | K111: N/A | L111: Marketing | M111: Content Creator | N111: 58316 | O111: Terminated | P111: Good | R111: =WEEKDAY(J112,2)=1 -> TRUE
B112: 00-26272875 | C112: Patrick | D112: Valdez | E112: Female | F112: Virginia | G112: Richmond | H112: Master | I112: 32372 | J112: 45264 | K112: N/A | L112: IT | M112: Software Developer | N112: 93697 | O112: Terminated | P112: Excellent | R112: =WEEKDAY(J113,2)=1 -> TRUE
B113: 00-26371663 | C113: Shelia | D113: Powell | E113: Female | F113: New York | G113: Rochester | H113: Bachelor | I113: 31657 | J113: 42695 | K113: N/A | L113: Marketing | M113: Marketing Manager | N113: 93466 | O113: Terminated | P113: Satisfactory | R113: =WEEKDAY(J114,2)=1 -> TRUE
B114: 00-26379293 | C114: Melanie | D114: Schroeder | E114: Female | F114: New York | G114: New York City | H114: Bachelor | I114: 27796 | J114: 42940 | K114: N/A | L114: Customer Service | M114: Help Desk Technician | N114: 70525 | O114: Terminated | P114: Good | R114: =WEEKDAY(J115,2)=1 -> TRUE
B115: 00-26442080 | C115: Louis | D115: Perez | E115: Female | F115: New York | G115: Buffalo | H115: High School | I115: 29327 | J115: 43458 | K115: N/A | L115: Operations | M115: Inventory Specialist | N115: 53068 | O115: Terminated | P115: Excellent | R115: =WEEKDAY(J116,2)=1 -> TRUE
B116: 00-27031212 | C116: David | D116: Delgado | E116: Female | F116: New York | G116: Rochester | H116: Bachelor | I116: 22589 | J116: 42961 | K116: N/A | L116: Customer Service | M116: Support Specialist | N116: 58327 | O116: Terminated | P116: Excellent | R116: =WEEKDAY(J117,2)=1 -> TRUE
B117: 00-27117564 | C117: Steven | D117: Boyer | E117: Female | F117: North Carolina | G117: Raleigh | H117: Bachelor | I117: 36482 | J117: 42590 | K117: N/A | L117: Marketing | M117: SEO Specialist | N117: 81943 | O117: Terminated | P117: Good | R117: =WEEKDAY(J118,2)=1 -> TRUE
B118: 00-27536261 | C118: Brenda | D118: Rogers | E118: Female | F118: Pennsylvania | G118: Allentown | H118: Bachelor | I118: 30000 | J118: 43591 | K118: N/A | L118: IT | M118: IT Support Specialist | N118: 60158 | O118: Terminated | P118: Satisfactory | R118: =WEEKDAY(J119,2)=1 -> TRUE
B119: 00-27748209 | C119: Zachary | D119: Gonzalez | E119: Female | F119: Pennsylvania | G119: Pittsburgh | H119: PhD | I119: 22622 | J119: 42184 | K119: N/A | L119: Sales | M119: Sales Manager | N119: 99440 | O119: Terminated | P119: Excellent | R119: =WEEKDAY(J120,2)=1 -> TRUE
... B126: 00-28634058 | C126: Megan | D126: Tyler | E126: Female | F126: Ohio | G126: Cincinnati | H126: Bachelor | I126: 30214 | J126: 45040 | K126: N/A | L126: Operations | M126: Logistics Coordinator | N126: 60079 | O126: Terminated | P126: Satisfactory | R126: =WEEKDAY(J127,2)=1 -> TRUE
B127: 00-28634797 | C127: Ashley | D127: Hernandez | E127: Female | F127: Pennsylvania | G127: Pittsburgh | H127: High School | I127: 36165 | J127: 42863 | K127: 43611 | L127: Operations | M127: Inventory Specialist | N127: 58307 | O127: Terminated | P127: Needs Improvement | R127: =WEEKDAY(J128,2)=1 -> TRUE
B128: 00-28971329 | C128: Ricky | D128: Lopez | E128: Female | F128: New York | G128: New York City | H128: Bachelor | I128: 31976 | J128: 44837 | K128: N/A | L128: IT | M128: Software Developer | N128: 93888 | O128: Terminated | P128: Good | R128: =WEEKDAY(J129,2)=1 -> TRUE
B129: 00-28975887 | C129: Kelly | D129: Washington | E129: Female | F129: New York | G129: Rochester | H129: High School | I129: 34811 | J129: 43045 | K129: N/A | L129: Operations | M129: Inventory Specialist | N129: 54146 | O129: Terminated | P129: Satisfactory | R129: =WEEKDAY(J130,2)=1 -> TRUE
B130: 00-28982195 | C130: Brian | D130: Frye | E130: Female | F130: New York | G130: New York City | H130: Bachelor | I130: 37524 | J130: 43318 | K130: 43498 | L130: Operations | M130: Logistics Coordinator | N130: 54814 | O130: Terminated | P130: Good | R130: =WEEKDAY(J131,2)=1 -> TRUE
...

Sheet AVG SALARY,OVERALL% AVG
A1: ALL Departments | C1: =COUNTA(STAFF!A:A) -> 8951 | E1: =AVERAGE(STAFF!M:M) -> 70964.214 | J1: =MAX(STAFF!M:M) -> 149377
A4: Deparments | C4: Head Count | E4: AVG Salary | G4: % Diff from overall avg | J4: Highest Salary
A5: Customer Service | C5: =COUNTIFS(STAFF!K1:K19000,A5) -> 1673 | E5: =AVERAGEIFS(STAFF!M:M,STAFF!K:K,A5) -> 65837.729 | G5: =E5-$E$1 -> -5126.4849 | J5: =_xlfn.MAXIFS(STAFF!M:M,STAFF!K:K,A5) -> 104359
A6: Operations | C6: =COUNTIFS(STAFF!K2:K19001,A6) -> 2718 | E6: =AVERAGEIFS(STAFF!M:M,STAFF!K:K,A6) -> 65400.25 | G6: =E6-$E$1 -> -5563.9633 | J6: =_xlfn.MAXIFS(STAFF!M:M,STAFF!K:K,A6) -> 115534
A7: Finance | C7: =COUNTIFS(STAFF!K3:K19002,A7) -> 452 | E7: =AVERAGEIFS(STAFF!M:M,STAFF!K:K,A7) -> 76451.144 | G7: =E7-$E$1 -> 5486.9303 | J7: =_xlfn.MAXIFS(STAFF!M:M,STAFF!K:K,A7) -> 149377
A8: Sales | C8: =COUNTIFS(STAFF!K4:K19003,A8) -> 1835 | E8: =AVERAGEIFS(STAFF!M:M,STAFF!K:K,A8) -> 76204.948 | G8: =E8-$E$1 -> 5240.7342 | J8: =_xlfn.MAXIFS(STAFF!M:M,STAFF!K:K,A8) -> 135055
A9: Marketing | C9: =COUNTIFS(STAFF!K5:K19004,A9) -> 718 | E9: =AVERAGEIFS(STAFF!M:M,STAFF!K:K,A9) -> 67659.024 | G9: =E9-$E$1 -> -3305.1898 | J9: =_xlfn.MAXIFS(STAFF!M:M,STAFF!K:K,A9) -> 110729
A10: HR | C10: =COUNTIFS(STAFF!K6:K19005,A10) -> 172 | E10: =AVERAGEIFS(STAFF!M:M,STAFF!K:K,A10) -> 64145.035 | G10: =E10-$E$1 -> -6819.1786 | J10: =_xlfn.MAXIFS(STAFF!M:M,STAFF!K:K,A10) -> 82203
A11: IT | C11: =COUNTIFS(STAFF!K7:K19006,A11) -> 1382 | E11: =AVERAGEIFS(STAFF!M:M,STAFF!K:K,A11) -> 81925.608 | G11: =E11-$E$1 -> 10961.394 | J11: =_xlfn.MAXIFS(STAFF!M:M,STAFF!K:K,A11) -> 133425

Sheet PIE CHART GENDER (DEPT)
A3: Row Labels | B3: Count of Employee_ID
A4: Customer Service | B4: 779
A5: Finance | B5: 210
A6: HR | B6: 94
A7: IT | B7: 601
A8: Marketing | B8: 352
A9: Operations | B9: 1250
A10: Sales | B10: 863
A11: Grand Total | B11: 4149

Sheet WORKFORCE SPREAD BY POSITION
A3: Row Labels | B3: Count of Atrrition status
A4: Accountant | B4: 173
A5: Accounts Payable Specialist | B5: 109
A6: Content Creator | B6: 308
A7: Customer Service Manager | B7: 74
A8: Customer Service Representative | B8: 503
A9: Finance Manager | B9: 9
A10: Financial Analyst | B10: 161
A11: Help Desk Technician | B11: 488
A12: HR Assistant | B12: 30
A13: HR Coordinator | B13: 56
A14: HR Manager | B14: 1
A15: Inventory Specialist | B15: 1044
... A32: Grand Total | B32: 8950

Sheet EMPLOYEE COUNT  BY SALARY
A3: Row Labels | B3: Count of Employee_ID | C3: Sum of Salary
A4: Customer Service | B4: 1673 | C4: 110146520
A5: Finance | B5: 452 | C5: 34555917
A6: HR | B6: 172 | C6: 11032946
A7: IT | B7: 1382 | C7: 113221190
A8: Marketing | B8: 718 | C8: 48579179
A9: Operations | B9: 2718 | C9: 177757880
A10: Sales | B10: 1835 | C10: 139836079
A11: Grand Total | B11: 8950 | C11: 635129711

Sheet MONTHLY TREND LINE
A3: Row Labels | B3: Count of Employee_ID
A4: Jan | B4: 734
A5: Feb | B5: 774
A6: Mar | B6: 761
A7: Apr | B7: 719
A8: May | B8: 755
A9: Jun | B9: 774
A10: Jul | B10: 747
A11: Aug | B11: 745
A12: Sep | B12: 753
A13: Oct | B13: 729
A14: Nov | B14: 734
A15: Dec | B15: 725
A16: Grand Total | B16: 8950

Sheet COUNT OF DEPT(PERFORMANCE)
A3: Department | B3: Count of Performance Rating
A4: Customer Service | B4: 779
A5: Finance | B5: 210
A6: HR | B6: 94
A7: IT | B7: 601
A8: Marketing | B8: 352
A9: Operations | B9: 1250
A10: Sales | B10: 863
A11: Grand Total | B11: 4149

Sheet TOP 10 EMPLOYEES
A1: Department | B1: (All)
A3: Row Labels | B3: Max of Salary
A4: Barbara | B4: 134173
A5: Gregory | B5: 132723
A6: Holly | B6: 133425
A7: Jose | B7: 141543
A8: Kristina | B8: 149377
A9: Lisa | B9: 131830
A10: Michael | B10: 132590
A11: Michelle | B11: 135055
A12: Raymond | B12: 133044
A13: Vincent | B13: 133039
A14: Grand Total | B14: 149377

Sheet PERFORMANCE RATING 
F1: - Performance Rating Analysis:
A3: Count of Employee_ID | B3: Column Labels
A4: Row Labels | B4: Excellent | C4: Good | D4: Needs Improvement | E4: Satisfactory | F4: Grand Total
A5: Customer Service | B5: 228 | C5: 611 | D5: 329 | E5: 505 | F5: 1673
A6: Finance | B6: 96 | C6: 202 | D6: 39 | E6: 115 | F6: 452
A7: HR | B7: 30 | C7: 75 | D7: 23 | E7: 44 | F7: 172
A8: IT | B8: 261 | C8: 583 | D8: 158 | E8: 380 | F8: 1382
A9: Marketing | B9: 108 | C9: 275 | D9: 124 | E9: 211 | F9: 718
A10: Operations | B10: 409 | C10: 1198 | D10: 322 | E10: 789 | F10: 2718
A11: Sales | B11: 434 | C11: 819 | D11: 128 | E11: 454 | F11: 1835
A12: Grand Total | B12: 1566 | C12: 3763 | D12: 1123 | E12: 2498 | F12: 8950

Sheet EMPLOYEE EDUCATION SNAPSHOT
A3: Row Labels | B3: Average of Salary
A4: Bachelor | B4: 69921.571
A5: High School | B5: 62144.287
A6: Master | B6: 82675.957
A7: PhD | B7: 86033.197
A8: Grand Total | B8: 70964.214
